Workbook

Sheet Master Dashboard
A1: SmartOps | MIS Management System — Master Dashboard
A2: Executive overview • Formula-driven KPIs, operational breakdown tables, and performance charts
A4: Total Orders | D4: Delivered Orders | G4: Pending / Processing Orders | J4: Total Order Value
A5: =COUNTA(OrdersTable[Order ID]) -> 60 | D5: =COUNTIF(OrdersTable[Order Status],"Delivered") -> 34 | G5: =COUNTIF(OrdersTable[Order Status],"Pending")+COUNTIF(OrdersTable[Order Status],"Processing") -> 21 | J5: =SUM(OrdersTable[Order Value (₹)]) -> 452183
A8: Inventory Value | D8: Low-Stock Products | G8: Completed Field Activities | J8: Overdue Checklist Tasks
A9: =SUM(InventoryTable[Inventory Value (₹)]) -> 384115 | D9: =COUNTIF(InventoryTable[Reorder Alert],"REORDER") -> 4 | G9: =COUNTIF(FMSTable[Status],"Completed") -> 27 | J9: =COUNTIF(ChecklistTable[Compliance Status],"Overdue") -> 16
A13: Order Status | B13: Count | D13: Inventory Status | E13: Products | G13: Employee | H13: Completed Activities | J13: Task Compliance | K13: Count
A14: Delivered | B14: =COUNTIF(OrdersTable[Order Status],A14) -> 34 | D14: OK | E14: =COUNTIF(InventoryTable[Reorder Alert],"OK") -> 6 | G14: Aarav Sharma | H14: =COUNTIFS(FMSTable[Employee Name (XLOOKUP)],G14,FMSTable[Status],"Completed") -> 3 | J14: On Time | K14: =COUNTIF(ChecklistTable[Compliance Status],J14) -> 30
A15: Pending | B15: =COUNTIF(OrdersTable[Order Status],A15) -> 8 | D15: REORDER | E15: =COUNTIF(InventoryTable[Reorder Alert],"REORDER") -> 4 | G15: Diya Verma | H15: =COUNTIFS(FMSTable[Employee Name (XLOOKUP)],G15,FMSTable[Status],"Completed") -> 2 | J15: Delayed | K15: =COUNTIF(ChecklistTable[Compliance Status],J15) -> 14
A16: Processing | B16: =COUNTIF(OrdersTable[Order Status],A16) -> 13 | D16: Total | E16: =SUM(E14:E15) -> 10 | G16: Kabir Patel | H16: =COUNTIFS(FMSTable[Employee Name (XLOOKUP)],G16,FMSTable[Status],"Completed") -> 3 | J16: Overdue | K16: =COUNTIF(ChecklistTable[Compliance Status],J16) -> 16
A17: Cancelled | B17: =COUNTIF(OrdersTable[Order Status],A17) -> 1 | G17: Meera Singh | H17: =COUNTIFS(FMSTable[Employee Name (XLOOKUP)],G17,FMSTable[Status],"Completed") -> 2 | J17: Pending | K17: =COUNTIF(ChecklistTable[Compliance Status],J17) -> 10
A18: Returned | B18: =COUNTIF(OrdersTable[Order Status],A18) -> 4 | G18: Ishaan Gupta | H18: =COUNTIFS(FMSTable[Employee Name (XLOOKUP)],G18,FMSTable[Status],"Completed") -> 4 | J18: Total | K18: =SUM(K14:K17) -> 70
A19: Total | B19: =SUM(B14:B18) -> 60 | G19: Ananya Rao | H19: =COUNTIFS(FMSTable[Employee Name (XLOOKUP)],G19,FMSTable[Status],"Completed") -> 2
G20: Rohan Das | H20: =COUNTIFS(FMSTable[Employee Name (XLOOKUP)],G20,FMSTable[Status],"Completed") -> 3
G21: Sana Khan | H21: =COUNTIFS(FMSTable[Employee Name (XLOOKUP)],G21,FMSTable[Status],"Completed") -> 3
G22: Vivaan Joshi | H22: =COUNTIFS(FMSTable[Employee Name (XLOOKUP)],G22,FMSTable[Status],"Completed") -> 2
G23: Ira Nair | H23: =COUNTIFS(FMSTable[Employee Name (XLOOKUP)],G23,FMSTable[Status],"Completed") -> 3
G24: Total | H24: =SUM(H14:H23) -> 27

Sheet FMS Dashboard
A1: FMS Dashboard — Field Activity & Turnaround Time (TAT) Monitor
A2: Full date-time TAT subtraction (accurately handling cross-midnight activities), SLA tracking, and employee productivity
A4: Completed Activities | C4: Pending Activities | E4: In-Progress Activities | G4: Average TAT (Hours) | I4: Delayed Completed (>4h)
A5: =COUNTIF(FMSTable[Status],"Completed") -> 27 | C5: =COUNTIF(FMSTable[Status],"Pending") -> 11 | E5: =COUNTIF(FMSTable[Status],"In Progress") -> 10 | G5: =IFERROR(AVERAGE(FMSTable[TAT (Hours)]),0) -> 7.3240741 | I5: =COUNTIF(FMSTable[SLA Result],"Delayed") -> 19
A9: Employee | B9: Completed | C9: Avg TAT (hrs) | D9: Within SLA (<=4h)
A10: Aarav Sharma | B10: =COUNTIFS(FMSTable[Employee Name (XLOOKUP)],A10,FMSTable[Status],"Completed") -> 3 | C10: =IFERROR(AVERAGEIFS(FMSTable[TAT (Hours)],FMSTable[Employee Name (XLOOKUP)],A10,FMSTable[Status],"Completed"),0) -> 5 | D10: =COUNTIFS(FMSTable[Employee Name (XLOOKUP)],A10,FMSTable[SLA Result],"Within SLA") -> 1
A11: Diya Verma | B11: =COUNTIFS(FMSTable[Employee Name (XLOOKUP)],A11,FMSTable[Status],"Completed") -> 2 | C11: =IFERROR(AVERAGEIFS(FMSTable[TAT (Hours)],FMSTable[Employee Name (XLOOKUP)],A11,FMSTable[Status],"Completed"),0) -> 7.5 | D11: =COUNTIFS(FMSTable[Employee Name (XLOOKUP)],A11,FMSTable[SLA Result],"Within SLA") -> 0
A12: Kabir Patel | B12: =COUNTIFS(FMSTable[Employee Name (XLOOKUP)],A12,FMSTable[Status],"Completed") -> 3 | C12: =IFERROR(AVERAGEIFS(FMSTable[TAT (Hours)],FMSTable[Employee Name (XLOOKUP)],A12,FMSTable[Status],"Completed"),0) -> 6.4166667 | D12: =COUNTIFS(FMSTable[Employee Name (XLOOKUP)],A12,FMSTable[SLA Result],"Within SLA") -> 1
A13: Meera Singh | B13: =COUNTIFS(FMSTable[Employee Name (XLOOKUP)],A13,FMSTable[Status],"Completed") -> 2 | C13: =IFERROR(AVERAGEIFS(FMSTable[TAT (Hours)],FMSTable[Employee Name (XLOOKUP)],A13,FMSTable[Status],"Completed"),0) -> 13 | D13: =COUNTIFS(FMSTable[Employee Name (XLOOKUP)],A13,FMSTable[SLA Result],"Within SLA") -> 0
A14: Ishaan Gupta | B14: =COUNTIFS(FMSTable[Employee Name (XLOOKUP)],A14,FMSTable[Status],"Completed") -> 4 | C14: =IFERROR(AVERAGEIFS(FMSTable[TAT (Hours)],FMSTable[Employee Name (XLOOKUP)],A14,FMSTable[Status],"Completed"),0) -> 10.625 | D14: =COUNTIFS(FMSTable[Employee Name (XLOOKUP)],A14,FMSTable[SLA Result],"Within SLA") -> 1
A15: Ananya Rao | B15: =COUNTIFS(FMSTable[Employee Name (XLOOKUP)],A15,FMSTable[Status],"Completed") -> 2 | C15: =IFERROR(AVERAGEIFS(FMSTable[TAT (Hours)],FMSTable[Employee Name (XLOOKUP)],A15,FMSTable[Status],"Completed"),0) -> 3.125 | D15: =COUNTIFS(FMSTable[Employee Name (XLOOKUP)],A15,FMSTable[SLA Result],"Within SLA") -> 1
A16: Rohan Das | B16: =COUNTIFS(FMSTable[Employee Name (XLOOKUP)],A16,FMSTable[Status],"Completed") -> 3 | C16: =IFERROR(AVERAGEIFS(FMSTable[TAT (Hours)],FMSTable[Employee Name (XLOOKUP)],A16,FMSTable[Status],"Completed"),0) -> 3.5 | D16: =COUNTIFS(FMSTable[Employee Name (XLOOKUP)],A16,FMSTable[SLA Result],"Within SLA") -> 2
A17: Sana Khan | B17: =COUNTIFS(FMSTable[Employee Name (XLOOKUP)],A17,FMSTable[Status],"Completed") -> 3 | C17: =IFERROR(AVERAGEIFS(FMSTable[TAT (Hours)],FMSTable[Employee Name (XLOOKUP)],A17,FMSTable[Status],"Completed"),0) -> 11.333333 | D17: =COUNTIFS(FMSTable[Employee Name (XLOOKUP)],A17,FMSTable[SLA Result],"Within SLA") -> 0
A18: Vivaan Joshi | B18: =COUNTIFS(FMSTable[Employee Name (XLOOKUP)],A18,FMSTable[Status],"Completed") -> 2 | C18: =IFERROR(AVERAGEIFS(FMSTable[TAT (Hours)],FMSTable[Employee Name (XLOOKUP)],A18,FMSTable[Status],"Completed"),0) -> 5 | D18: =COUNTIFS(FMSTable[Employee Name (XLOOKUP)],A18,FMSTable[SLA Result],"Within SLA") -> 1
A19: Ira Nair | B19: =COUNTIFS(FMSTable[Employee Name (XLOOKUP)],A19,FMSTable[Status],"Completed") -> 3 | C19: =IFERROR(AVERAGEIFS(FMSTable[TAT (Hours)],FMSTable[Employee Name (XLOOKUP)],A19,FMSTable[Status],"Completed"),0) -> 6.4166667 | D19: =COUNTIFS(FMSTable[Employee Name (XLOOKUP)],A19,FMSTable[SLA Result],"Within SLA") -> 1
A20: Total / Overall Avg | B20: =SUM(B10:B19) -> 27 | C20: =IFERROR(AVERAGE(FMSTable[TAT (Hours)]),0) -> 7.3240741 | D20: =SUM(D10:D19) -> 8
A24: Cross-Midnight & Recent Field Activity TAT Verification Log (Live Linked to FMSTable)
A25: Activity ID | B25: Activity Date | C25: Employee ID | D25: Employee Name | E25: Activity Type | F25: Assignment Date/Time | G25: Completion Date/Time | H25: Status | I25: TAT (Hours) | J25: SLA Result
A26: ='Raw Data'!A5 -> FMS0001 | B26: ='Raw Data'!B5 -> 46311 | C26: ='Raw Data'!C5 -> E004 | D26: ='Raw Data'!D5 -> Meera Singh | E26: ='Raw Data'!E5 -> Site Visit | F26: ='Raw Data'!F5 -> 46311.365 | G26: ='Raw Data'!G5 -> 46311.906 | H26: ='Raw Data'!H5 -> Completed | ... J26: ='Raw Data'!J5 -> Delayed
A27: ='Raw Data'!A7 -> FMS0003 | B27: ='Raw Data'!B7 -> 46309 | C27: ='Raw Data'!C7 -> E010 | D27: ='Raw Data'!D7 -> Ira Nair | E27: ='Raw Data'!E7 -> Customer Follow-up | F27: ='Raw Data'!F7 -> 46309.885 | G27: ='Raw Data'!G7 -> 46309.938 | H27: ='Raw Data'!H7 -> Completed | ... J27: ='Raw Data'!J7 -> Within SLA
A28: ='Raw Data'!A8 -> FMS0004 | B28: ='Raw Data'!B8 -> 46271 | C28: ='Raw Data'!C8 -> E003 | D28: ='Raw Data'!D8 -> Kabir Patel | E28: ='Raw Data'!E8 -> Delivery Verification | F28: ='Raw Data'!F8 -> 46271.885 | G28: ='Raw Data'!G8 -> 46272.219 | H28: ='Raw Data'!H8 -> Completed | ... J28: ='Raw Data'!J8 -> Delayed
A29: ='Raw Data'!A12 -> FMS0008 | B29: ='Raw Data'!B12 -> 46306 | C29: ='Raw Data'!C12 -> E005 | D29: ='Raw Data'!D12 -> Ishaan Gupta | E29: ='Raw Data'!E12 -> Stock Audit | F29: ='Raw Data'!F12 -> 46306.771 | G29: ='Raw Data'!G12 -> 46307.312 | H29: ='Raw Data'!H12 -> Completed | ... J29: ='Raw Data'!J12 -> Delayed
A30: ='Raw Data'!A20 -> FMS0016 | B30: ='Raw Data'!B20 -> 46267 | C30: ='Raw Data'!C20 -> E009 | D30: ='Raw Data'!D20 -> Vivaan Joshi | E30: ='Raw Data'!E20 -> Delivery Verification | F30: ='Raw Data'!F20 -> 46267.677 | G30: ='Raw Data'!G20 -> 46268.01 | H30: ='Raw Data'!H20 -> Completed | ... J30: ='Raw Data'!J20 -> Delayed
A31: ='Raw Data'!A21 -> FMS0017 | B31: ='Raw Data'!B21 -> 46301 | C31: ='Raw Data'!C21 -> E002 | D31: ='Raw Data'!D21 -> Diya Verma | E31: ='Raw Data'!E21 -> Document Collection | F31: ='Raw Data'!F21 -> 46301.812 | G31: ='Raw Data'!G21 -> 46302.229 | H31: ='Raw Data'!H21 -> Completed | ... J31: ='Raw Data'!J21 -> Delayed
A32: ='Raw Data'!A22 -> FMS0018 | B32: ='Raw Data'!B22 -> 46260 | C32: ='Raw Data'!C22 -> E005 | D32: ='Raw Data'!D22 -> Ishaan Gupta | E32: ='Raw Data'!E22 -> Quality Check | F32: ='Raw Data'!F22 -> 46260.531 | G32: ='Raw Data'!G22 -> 46261.073 | H32: ='Raw Data'!H22 -> Completed | ... J32: ='Raw Data'!J22 -> Delayed
A33: ='Raw Data'!A27 -> FMS0023 | B33: ='Raw Data'!B27 -> 46310 | C33: ='Raw Data'!C27 -> E010 | D33: ='Raw Data'!D27 -> Ira Nair | E33: ='Raw Data'!E27 -> Document Collection | F33: ='Raw Data'!F27 -> 46310.927 | G33: ='Raw Data'!G27 -> 46311.469 | H33: ='Raw Data'!H27 -> Completed | ... J33: ='Raw Data'!J27 -> Delayed
A34: ='Raw Data'!A42 -> FMS0038 | B34: ='Raw Data'!B42 -> 46307 | C34: ='Raw Data'!C42 -> E005 | D34: ='Raw Data'!D42 -> Ishaan Gupta | E34: ='Raw Data'!E42 -> Stock Audit | F34: ='Raw Data'!F42 -> 46307.938 | G34: ='Raw Data'!G42 -> 46308.083 | H34: ='Raw Data'!H42 -> Completed | ... J34: ='Raw Data'!J42 -> Within SLA
A35: ='Raw Data'!A53 -> FMS0049 | B35: ='Raw Data'!B53 -> 46314 | C35: ='Raw Data'!C53 -> E008 | D35: ='Raw Data'!D53 -> Sana Khan | E35: ='Raw Data'!E53 -> Site Visit | F35: ='Raw Data'!F53 -> 46314.521 | G35: ='Raw Data'!G53 -> 46315.062 | H35: ='Raw Data'!H53 -> Completed | ... J35: ='Raw Data'!J53 -> Delayed

Sheet Checklist Dashboard
A1: Checklist Dashboard — Task Execution & On-Time Compliance
A2: Monitoring completed, pending, overdue, and delayed tasks with employee-level SLA compliance breakdown
A4: Completed Tasks | C4: Pending Tasks | E4: Overdue Tasks | G4: Delayed Tasks | I4: Task Completion Rate | K4: On-Time Compliance
A5: =COUNTIF(ChecklistTable[Task Status],"Completed") -> 44 | C5: =COUNTIF(ChecklistTable[Compliance Status],"Pending") -> 10 | E5: =COUNTIF(ChecklistTable[Compliance Status],"Overdue") -> 16 | G5: =COUNTIF(ChecklistTable[Compliance Status],"Delayed") -> 14 | I5: =IFERROR(COUNTIF(ChecklistTable[Task Status],"Completed")/COUNTA(ChecklistTable[Task ID]),0) -> 0.62857143 | K5: =IFERROR(COUNTIF(ChecklistTable[Compliance Status],"On Time")/COUNTIF(ChecklistTable[Task Status],"Completed"),0) -> 0.68181818
A8: Compliance Status Summary
A9: Compliance Status | B9: Task Count | C9: Share (%)
A10: On Time | B10: =COUNTIF(ChecklistTable[Compliance Status],A10) -> 30 | C10: =IFERROR(B10/$B$14,0) -> 0.42857143
A11: Delayed | B11: =COUNTIF(ChecklistTable[Compliance Status],A11) -> 14 | C11: =IFERROR(B11/$B$14,0) -> 0.2
A12: Overdue | B12: =COUNTIF(ChecklistTable[Compliance Status],A12) -> 16 | C12: =IFERROR(B12/$B$14,0) -> 0.22857143
A13: Pending | B13: =COUNTIF(ChecklistTable[Compliance Status],A13) -> 10 | C13: =IFERROR(B13/$B$14,0) -> 0.14285714
A14: Total | B14: =SUM(B10:B13) -> 70 | C14: =SUM(C10:C13) -> 1
A23: Employee Checklist Compliance Breakdown
A24: Employee Name | B24: Total Assigned | C24: Completed | D24: On Time | E24: Delayed | F24: Overdue | G24: On-Time Rate
A25: Aarav Sharma | B25: =COUNTIF(ChecklistTable[Employee Name (XLOOKUP)],A25) -> 7 | C25: =COUNTIFS(ChecklistTable[Employee Name (XLOOKUP)],A25,ChecklistTable[Task Status],"Completed") -> 5 | D25: =COUNTIFS(ChecklistTable[Employee Name (XLOOKUP)],A25,ChecklistTable[Compliance Status],"On Time") -> 3 | E25: =COUNTIFS(ChecklistTable[Employee Name (XLOOKUP)],A25,ChecklistTable[Compliance Status],"Delayed") -> 2 | F25: =COUNTIFS(ChecklistTable[Employee Name (XLOOKUP)],A25,ChecklistTable[Compliance Status],"Overdue") -> 2 | G25: =IFERROR(D25/C25,0) -> 0.6
A26: Diya Verma | B26: =COUNTIF(ChecklistTable[Employee Name (XLOOKUP)],A26) -> 7 | C26: =COUNTIFS(ChecklistTable[Employee Name (XLOOKUP)],A26,ChecklistTable[Task Status],"Completed") -> 5 | D26: =COUNTIFS(ChecklistTable[Employee Name (XLOOKUP)],A26,ChecklistTable[Compliance Status],"On Time") -> 2 | E26: =COUNTIFS(ChecklistTable[Employee Name (XLOOKUP)],A26,ChecklistTable[Compliance Status],"Delayed") -> 3 | F26: =COUNTIFS(ChecklistTable[Employee Name (XLOOKUP)],A26,ChecklistTable[Compliance Status],"Overdue") -> 1 | G26: =IFERROR(D26/C26,0) -> 0.4
A27: Kabir Patel | B27: =COUNTIF(ChecklistTable[Employee Name (XLOOKUP)],A27) -> 7 | C27: =COUNTIFS(ChecklistTable[Employee Name (XLOOKUP)],A27,ChecklistTable[Task Status],"Completed") -> 5 | D27: =COUNTIFS(ChecklistTable[Employee Name (XLOOKUP)],A27,ChecklistTable[Compliance Status],"On Time") -> 3 | E27: =COUNTIFS(ChecklistTable[Employee Name (XLOOKUP)],A27,ChecklistTable[Compliance Status],"Delayed") -> 2 | F27: =COUNTIFS(ChecklistTable[Employee Name (XLOOKUP)],A27,ChecklistTable[Compliance Status],"Overdue") -> 1 | G27: =IFERROR(D27/C27,0) -> 0.6
A28: Meera Singh | B28: =COUNTIF(ChecklistTable[Employee Name (XLOOKUP)],A28) -> 7 | C28: =COUNTIFS(ChecklistTable[Employee Name (XLOOKUP)],A28,ChecklistTable[Task Status],"Completed") -> 3 | D28: =COUNTIFS(ChecklistTable[Employee Name (XLOOKUP)],A28,ChecklistTable[Compliance Status],"On Time") -> 3 | E28: =COUNTIFS(ChecklistTable[Employee Name (XLOOKUP)],A28,ChecklistTable[Compliance Status],"Delayed") -> 0 | F28: =COUNTIFS(ChecklistTable[Employee Name (XLOOKUP)],A28,ChecklistTable[Compliance Status],"Overdue") -> 3 | G28: =IFERROR(D28/C28,0) -> 1
A29: Ishaan Gupta | B29: =COUNTIF(ChecklistTable[Employee Name (XLOOKUP)],A29) -> 7 | C29: =COUNTIFS(ChecklistTable[Employee Name (XLOOKUP)],A29,ChecklistTable[Task Status],"Completed") -> 6 | D29: =COUNTIFS(ChecklistTable[Employee Name (XLOOKUP)],A29,ChecklistTable[Compliance Status],"On Time") -> 3 | E29: =COUNTIFS(ChecklistTable[Employee Name (XLOOKUP)],A29,ChecklistTable[Compliance Status],"Delayed") -> 3 | F29: =COUNTIFS(ChecklistTable[Employee Name (XLOOKUP)],A29,ChecklistTable[Compliance Status],"Overdue") -> 1 | G29: =IFERROR(D29/C29,0) -> 0.5
A30: Ananya Rao | B30: =COUNTIF(ChecklistTable[Employee Name (XLOOKUP)],A30) -> 7 | C30: =COUNTIFS(ChecklistTable[Employee Name (XLOOKUP)],A30,ChecklistTable[Task Status],"Completed") -> 5 | D30: =COUNTIFS(ChecklistTable[Employee Name (XLOOKUP)],A30,ChecklistTable[Compliance Status],"On Time") -> 4 | E30: =COUNTIFS(ChecklistTable[Employee Name (XLOOKUP)],A30,ChecklistTable[Compliance Status],"Delayed") -> 1 | F30: =COUNTIFS(ChecklistTable[Employee Name (XLOOKUP)],A30,ChecklistTable[Compliance Status],"Overdue") -> 1 | G30: =IFERROR(D30/C30,0) -> 0.8
A31: Rohan Das | B31: =COUNTIF(ChecklistTable[Employee Name (XLOOKUP)],A31) -> 7 | C31: =COUNTIFS(ChecklistTable[Employee Name (XLOOKUP)],A31,ChecklistTable[Task Status],"Completed") -> 6 | D31: =COUNTIFS(ChecklistTable[Employee Name (XLOOKUP)],A31,ChecklistTable[Compliance Status],"On Time") -> 5 | E31: =COUNTIFS(ChecklistTable[Employee Name (XLOOKUP)],A31,ChecklistTable[Compliance Status],"Delayed") -> 1 | F31: =COUNTIFS(ChecklistTable[Employee Name (XLOOKUP)],A31,ChecklistTable[Compliance Status],"Overdue") -> 1 | G31: =IFERROR(D31/C31,0) -> 0.83333333
A32: Sana Khan | B32: =COUNTIF(ChecklistTable[Employee Name (XLOOKUP)],A32) -> 7 | C32: =COUNTIFS(ChecklistTable[Employee Name (XLOOKUP)],A32,ChecklistTable[Task Status],"Completed") -> 2 | D32: =COUNTIFS(ChecklistTable[Employee Name (XLOOKUP)],A32,ChecklistTable[Compliance Status],"On Time") -> 1 | E32: =COUNTIFS(ChecklistTable[Employee Name (XLOOKUP)],A32,ChecklistTable[Compliance Status],"Delayed") -> 1 | F32: =COUNTIFS(ChecklistTable[Employee Name (XLOOKUP)],A32,ChecklistTable[Compliance Status],"Overdue") -> 4 | G32: =IFERROR(D32/C32,0) -> 0.5
A33: Vivaan Joshi | B33: =COUNTIF(ChecklistTable[Employee Name (XLOOKUP)],A33) -> 7 | C33: =COUNTIFS(ChecklistTable[Employee Name (XLOOKUP)],A33,ChecklistTable[Task Status],"Completed") -> 3 | D33: =COUNTIFS(ChecklistTable[Employee Name (XLOOKUP)],A33,ChecklistTable[Compliance Status],"On Time") -> 3 | E33: =COUNTIFS(ChecklistTable[Employee Name (XLOOKUP)],A33,ChecklistTable[Compliance Status],"Delayed") -> 0 | F33: =COUNTIFS(ChecklistTable[Employee Name (XLOOKUP)],A33,ChecklistTable[Compliance Status],"Overdue") -> 2 | G33: =IFERROR(D33/C33,0) -> 1
A34: Ira Nair | B34: =COUNTIF(ChecklistTable[Employee Name (XLOOKUP)],A34) -> 7 | C34: =COUNTIFS(ChecklistTable[Employee Name (XLOOKUP)],A34,ChecklistTable[Task Status],"Completed") -> 4 | D34: =COUNTIFS(ChecklistTable[Employee Name (XLOOKUP)],A34,ChecklistTable[Compliance Status],"On Time") -> 3 | E34: =COUNTIFS(ChecklistTable[Employee Name (XLOOKUP)],A34,ChecklistTable[Compliance Status],"Delayed") -> 1 | F34: =COUNTIFS(ChecklistTable[Employee Name (XLOOKUP)],A34,ChecklistTable[Compliance Status],"Overdue") -> 0 | G34: =IFERROR(D34/C34,0) -> 0.75
A35: Total / Overall | B35: =SUM(B25:B34) -> 70 | C35: =SUM(C25:C34) -> 44 | D35: =SUM(D25:D34) -> 30 | E35: =SUM(E25:E34) -> 14 | F35: =SUM(F25:F34) -> 16 | G35: =IFERROR(D35/C35,0) -> 0.68181818

Sheet Order Tracking
A1: Order Tracking
A2: Order lifecycle register with XLOOKUP employee details, status dropdowns, overdue flags, and quality checks
A3: Order ID | B3: Order Date | C3: Customer | D3: Product ID | E3: Product | F3: Quantity | G3: Unit Price (₹) | H3: Order Value (₹) | I3: Employee ID | J3: Employee Name (XLOOKUP) | K3: Order Status | L3: Expected Delivery | M3: Actual Delivery | N3: Overdue Status | P3: Order Audit & Summary | Q3: Status / Count
A4: ORD0001 | B4: 46310 | C4: Northstar Services | D4: P001 | E4: Wireless Mouse | F4: 2 | G4: 499 | H4: =F4*G4 -> 998 | I4: E001 | J4: =IFERROR(_xlfn.XLOOKUP(I4,EmployeeTable[Employee ID],EmployeeTable[Employee Name],"Not found"),IFERROR(INDEX(EmployeeTable[Employee Name],MATCH(I4,EmployeeTable[Employee ID],0)),"Not found")) -> Aarav Sharma | K4: Processing | L4: 46316 | N4: =IF(AND(OR(K4="Pending",K4="Processing"),L4<TODAY()),"Overdue","On Track") -> On Track | P4: Duplicate Order IDs | Q4: =IF(SUMPRODUCT(--(COUNTIF(OrdersTable[Order ID],OrdersTable[Order ID])>1))>0,"DUPLICATES FOUND","IDs unique") -> IDs unique
A5: ORD0002 | B5: 46311 | C5: BluePeak Retail | D5: P002 | E5: Keyboard | F5: 4 | G5: 899 | H5: =F5*G5 -> 3596 | I5: E002 | J5: =IFERROR(_xlfn.XLOOKUP(I5,EmployeeTable[Employee ID],EmployeeTable[Employee Name],"Not found"),IFERROR(INDEX(EmployeeTable[Employee Name],MATCH(I5,EmployeeTable[Employee ID],0)),"Not found")) -> Diya Verma | K5: Processing | L5: 46317 | N5: =IF(AND(OR(K5="Pending",K5="Processing"),L5<TODAY()),"Overdue","On Track") -> On Track | P5: Missing Customer/Product | Q5: =IF(COUNTBLANK(OrdersTable[Customer])+COUNTBLANK(OrdersTable[Product ID])>0,"MISSING VALUES","Complete") -> Complete
A6: ORD0003 | B6: 46228 | C6: Cedar & Co. | D6: P003 | E6: USB-C Hub | F6: 12 | G6: 1499 | H6: =F6*G6 -> 17988 | I6: E003 | J6: =IFERROR(_xlfn.XLOOKUP(I6,EmployeeTable[Employee ID],EmployeeTable[Employee Name],"Not found"),IFERROR(INDEX(EmployeeTable[Employee Name],MATCH(I6,EmployeeTable[Employee ID],0)),"Not found")) -> Kabir Patel | K6: Delivered | L6: 46238 | M6: 46238 | N6: =IF(AND(OR(K6="Pending",K6="Processing"),L6<TODAY()),"Overdue","On Track") -> On Track | P6: Total Orders | Q6: =COUNTA(OrdersTable[Order ID]) -> 60
A7: ORD0004 | B7: 46310 | C7: Summit Logistics | D7: P004 | E7: Laptop Stand | F7: 1 | G7: 1199 | H7: =F7*G7 -> 1199 | I7: E004 | J7: =IFERROR(_xlfn.XLOOKUP(I7,EmployeeTable[Employee ID],EmployeeTable[Employee Name],"Not found"),IFERROR(INDEX(EmployeeTable[Employee Name],MATCH(I7,EmployeeTable[Employee ID],0)),"Not found")) -> Meera Singh | K7: Delivered | L7: 46313 | M7: 46314 | N7: =IF(AND(OR(K7="Pending",K7="Processing"),L7<TODAY()),"Overdue","On Track") -> On Track | P7: Delivered Orders | Q7: =COUNTIF(OrdersTable[Order Status],"Delivered") -> 34
A8: ORD0005 | B8: 46237 | C8: Orbit Systems | D8: P005 | E8: Webcam HD | F8: 1 | G8: 2499 | H8: =F8*G8 -> 2499 | I8: E005 | J8: =IFERROR(_xlfn.XLOOKUP(I8,EmployeeTable[Employee ID],EmployeeTable[Employee Name],"Not found"),IFERROR(INDEX(EmployeeTable[Employee Name],MATCH(I8,EmployeeTable[Employee ID],0)),"Not found")) -> Ishaan Gupta | K8: Delivered | L8: 46247 | M8: 46249 | N8: =IF(AND(OR(K8="Pending",K8="Processing"),L8<TODAY()),"Overdue","On Track") -> On Track | P8: Open (Pending/Proc.) | Q8: =COUNTIF(OrdersTable[Order Status],"Pending")+COUNTIF(OrdersTable[Order Status],"Processing") -> 21
A9: ORD0006 | B9: 46225 | C9: MapleWorks | D9: P006 | E9: Headset | F9: 9 | G9: 1799 | H9: =F9*G9 -> 16191 | I9: E006 | J9: =IFERROR(_xlfn.XLOOKUP(I9,EmployeeTable[Employee ID],EmployeeTable[Employee Name],"Not found"),IFERROR(INDEX(EmployeeTable[Employee Name],MATCH(I9,EmployeeTable[Employee ID],0)),"Not found")) -> Ananya Rao | K9: Delivered | L9: 46233 | M9: 46234 | N9: =IF(AND(OR(K9="Pending",K9="Processing"),L9<TODAY()),"Overdue","On Track") -> On Track | P9: Overdue Open Orders | Q9: =COUNTIF(OrdersTable[Overdue Status],"Overdue") -> 13
A10: ORD0007 | B10: 46279 | C10: BrightPath Consulting | D10: P007 | E10: Power Adapter | F10: 1 | G10: 999 | H10: =F10*G10 -> 999 | I10: E007 | J10: =IFERROR(_xlfn.XLOOKUP(I10,EmployeeTable[Employee ID],EmployeeTable[Employee Name],"Not found"),IFERROR(INDEX(EmployeeTable[Employee Name],MATCH(I10,EmployeeTable[Employee ID],0)),"Not found")) -> Rohan Das | K10: Processing | L10: 46283 | N10: =IF(AND(OR(K10="Pending",K10="Processing"),L10<TODAY()),"Overdue","On Track") -> Overdue | P10: Returned / Cancelled | Q10: =COUNTIF(OrdersTable[Order Status],"Returned")+COUNTIF(OrdersTable[Order Status],"Cancelled") -> 5
A11: ORD0008 | B11: 46271 | C11: UrbanCart | D11: P008 | E11: Notebook Pack | F11: 5 | G11: 249 | H11: =F11*G11 -> 1245 | I11: E008 | J11: =IFERROR(_xlfn.XLOOKUP(I11,EmployeeTable[Employee ID],EmployeeTable[Employee Name],"Not found"),IFERROR(INDEX(EmployeeTable[Employee Name],MATCH(I11,EmployeeTable[Employee ID],0)),"Not found")) -> Sana Khan | K11: Delivered | L11: 46275 | M11: 46275 | N11: =IF(AND(OR(K11="Pending",K11="Processing"),L11<TODAY()),"Overdue","On Track") -> On Track | P11: Total Order Value | Q11: =SUM(OrdersTable[Order Value (₹)]) -> 452183
A12: ORD0009 | B12: 46301 | C12: Silverline Traders | D12: P009 | E12: Ethernet Cable | F12: 2 | G12: 199 | H12: =F12*G12 -> 398 | I12: E009 | J12: =IFERROR(_xlfn.XLOOKUP(I12,EmployeeTable[Employee ID],EmployeeTable[Employee Name],"Not found"),IFERROR(INDEX(EmployeeTable[Employee Name],MATCH(I12,EmployeeTable[Employee ID],0)),"Not found")) -> Vivaan Joshi | K12: Delivered | L12: 46309 | M12: 46309 | N12: =IF(AND(OR(K12="Pending",K12="Processing"),L12<TODAY()),"Overdue","On Track") -> On Track
A13: ORD0010 | B13: 46237 | C13: Nova Office Solutions | D13: P010 | E13: Portable SSD | F13: 5 | G13: 4999 | H13: =F13*G13 -> 24995 | I13: E010 | J13: =IFERROR(_xlfn.XLOOKUP(I13,EmployeeTable[Employee ID],EmployeeTable[Employee Name],"Not found"),IFERROR(INDEX(EmployeeTable[Employee Name],MATCH(I13,EmployeeTable[Employee ID],0)),"Not found")) -> Ira Nair | K13: Processing | L13: 46239 | N13: =IF(AND(OR(K13="Pending",K13="Processing"),L13<TODAY()),"Overdue","On Track") -> Overdue
A14: ORD0011 | B14: 46246 | C14: Greenfield Labs | D14: P001 | E14: Wireless Mouse | F14: 2 | G14: 499 | H14: =F14*G14 -> 998 | I14: E001 | J14: =IFERROR(_xlfn.XLOOKUP(I14,EmployeeTable[Employee ID],EmployeeTable[Employee Name],"Not found"),IFERROR(INDEX(EmployeeTable[Employee Name],MATCH(I14,EmployeeTable[Employee ID],0)),"Not found")) -> Aarav Sharma | K14: Delivered | L14: 46254 | M14: 46254 | N14: =IF(AND(OR(K14="Pending",K14="Processing"),L14<TODAY()),"Overdue","On Track") -> On Track
A15: ORD0012 | B15: 46234 | C15: Pioneer Supplies | D15: P002 | E15: Keyboard | F15: 10 | G15: 899 | H15: =F15*G15 -> 8990 | I15: E002 | J15: =IFERROR(_xlfn.XLOOKUP(I15,EmployeeTable[Employee ID],EmployeeTable[Employee Name],"Not found"),IFERROR(INDEX(EmployeeTable[Employee Name],MATCH(I15,EmployeeTable[Employee ID],0)),"Not found")) -> Diya Verma | K15: Pending | L15: 46241 | N15: =IF(AND(OR(K15="Pending",K15="Processing"),L15<TODAY()),"Overdue","On Track") -> Overdue
A16: ORD0013 | B16: 46311 | C16: Northstar Services | D16: P003 | E16: USB-C Hub | F16: 1 | G16: 1499 | H16: =F16*G16 -> 1499 | I16: E003 | J16: =IFERROR(_xlfn.XLOOKUP(I16,EmployeeTable[Employee ID],EmployeeTable[Employee Name],"Not found"),IFERROR(INDEX(EmployeeTable[Employee Name],MATCH(I16,EmployeeTable[Employee ID],0)),"Not found")) -> Kabir Patel | K16: Processing | L16: 46318 | N16: =IF(AND(OR(K16="Pending",K16="Processing"),L16<TODAY()),"Overdue","On Track") -> On Track
A17: ORD0014 | B17: 46304 | C17: BluePeak Retail | D17: P004 | E17: Laptop Stand | F17: 4 | G17: 1199 | H17: =F17*G17 -> 4796 | I17: E004 | J17: =IFERROR(_xlfn.XLOOKUP(I17,EmployeeTable[Employee ID],EmployeeTable[Employee Name],"Not found"),IFERROR(INDEX(EmployeeTable[Employee Name],MATCH(I17,EmployeeTable[Employee ID],0)),"Not found")) -> Meera Singh | K17: Delivered | L17: 46307 | M17: 46307 | N17: =IF(AND(OR(K17="Pending",K17="Processing"),L17<TODAY()),"Overdue","On Track") -> On Track
A18: ORD0015 | B18: 46233 | C18: Cedar & Co. | D18: P005 | E18: Webcam HD | F18: 6 | G18: 2499 | H18: =F18*G18 -> 14994 | I18: E005 | J18: =IFERROR(_xlfn.XLOOKUP(I18,EmployeeTable[Employee ID],EmployeeTable[Employee Name],"Not found"),IFERROR(INDEX(EmployeeTable[Employee Name],MATCH(I18,EmployeeTable[Employee ID],0)),"Not found")) -> Ishaan Gupta | K18: Delivered | L18: 46237 | M18: 46236 | N18: =IF(AND(OR(K18="Pending",K18="Processing"),L18<TODAY()),"Overdue","On Track") -> On Track
A19: ORD0016 | B19: 46229 | C19: Summit Logistics | D19: P006 | E19: Headset | F19: 5 | G19: 1799 | H19: =F19*G19 -> 8995 | I19: E006 | J19: =IFERROR(_xlfn.XLOOKUP(I19,EmployeeTable[Employee ID],EmployeeTable[Employee Name],"Not found"),IFERROR(INDEX(EmployeeTable[Employee Name],MATCH(I19,EmployeeTable[Employee ID],0)),"Not found")) -> Ananya Rao | K19: Pending | L19: 46232 | N19: =IF(AND(OR(K19="Pending",K19="Processing"),L19<TODAY()),"Overdue","On Track") -> Overdue
A20: ORD0017 | B20: 46293 | C20: Orbit Systems | D20: P007 | E20: Power Adapter | F20: 9 | G20: 999 | H20: =F20*G20 -> 8991 | I20: E007 | J20: =IFERROR(_xlfn.XLOOKUP(I20,EmployeeTable[Employee ID],EmployeeTable[Employee Name],"Not found"),IFERROR(INDEX(EmployeeTable[Employee Name],MATCH(I20,EmployeeTable[Employee ID],0)),"Not found")) -> Rohan Das | K20: Delivered | L20: 46298 | M20: 46298 | N20: =IF(AND(OR(K20="Pending",K20="Processing"),L20<TODAY()),"Overdue","On Track") -> On Track
A21: ORD0018 | B21: 46280 | C21: MapleWorks | D21: P008 | E21: Notebook Pack | F21: 11 | G21: 249 | H21: =F21*G21 -> 2739 | I21: E008 | J21: =IFERROR(_xlfn.XLOOKUP(I21,EmployeeTable[Employee ID],EmployeeTable[Employee Name],"Not found"),IFERROR(INDEX(EmployeeTable[Employee Name],MATCH(I21,EmployeeTable[Employee ID],0)),"Not found")) -> Sana Khan | K21: Delivered | L21: 46290 | M21: 46290 | N21: =IF(AND(OR(K21="Pending",K21="Processing"),L21<TODAY()),"Overdue","On Track") -> On Track
A22: ORD0019 | B22: 46309 | C22: BrightPath Consulting | D22: P009 | E22: Ethernet Cable | F22: 4 | G22: 199 | H22: =F22*G22 -> 796 | I22: E009 | J22: =IFERROR(_xlfn.XLOOKUP(I22,EmployeeTable[Employee ID],EmployeeTable[Employee Name],"Not found"),IFERROR(INDEX(EmployeeTable[Employee Name],MATCH(I22,EmployeeTable[Employee ID],0)),"Not found")) -> Vivaan Joshi | K22: Processing | L22: 46315 | N22: =IF(AND(OR(K22="Pending",K22="Processing"),L22<TODAY()),"Overdue","On Track") -> On Track
A23: ORD0020 | B23: 46263 | C23: UrbanCart | D23: P010 | E23: Portable SSD | F23: 5 | G23: 4999 | H23: =F23*G23 -> 24995 | I23: E010 | J23: =IFERROR(_xlfn.XLOOKUP(I23,EmployeeTable[Employee ID],EmployeeTable[Employee Name],"Not found"),IFERROR(INDEX(EmployeeTable[Employee Name],MATCH(I23,EmployeeTable[Employee ID],0)),"Not found")) -> Ira Nair | K23: Delivered | L23: 46266 | M23: 46267 | N23: =IF(AND(OR(K23="Pending",K23="Processing"),L23<TODAY()),"Overdue","On Track") -> On Track
A24: ORD0021 | B24: 46274 | C24: Silverline Traders | D24: P001 | E24: Wireless Mouse | F24: 4 | G24: 499 | H24: =F24*G24 -> 1996 | I24: E001 | J24: =IFERROR(_xlfn.XLOOKUP(I24,EmployeeTable[Employee ID],EmployeeTable[Employee Name],"Not found"),IFERROR(INDEX(EmployeeTable[Employee Name],MATCH(I24,EmployeeTable[Employee ID],0)),"Not found")) -> Aarav Sharma | K24: Delivered | L24: 46283 | M24: 46285 | N24: =IF(AND(OR(K24="Pending",K24="Processing"),L24<TODAY()),"Overdue","On Track") -> On Track
A25: ORD0022 | B25: 46256 | C25: Nova Office Solutions | D25: P002 | E25: Keyboard | F25: 3 | G25: 899 | H25: =F25*G25 -> 2697 | I25: E002 | J25: =IFERROR(_xlfn.XLOOKUP(I25,EmployeeTable[Employee ID],EmployeeTable[Employee Name],"Not found"),IFERROR(INDEX(EmployeeTable[Employee Name],MATCH(I25,EmployeeTable[Employee ID],0)),"Not found")) -> Diya Verma | K25: Delivered | L25: 46262 | M25: 46264 | N25: =IF(AND(OR(K25="Pending",K25="Processing"),L25<TODAY()),"Overdue","On Track") -> On Track
A26: ORD0023 | B26: 46243 | C26: Greenfield Labs | D26: P003 | E26: USB-C Hub | F26: 9 | G26: 1499 | H26: =F26*G26 -> 13491 | I26: E003 | J26: =IFERROR(_xlfn.XLOOKUP(I26,EmployeeTable[Employee ID],EmployeeTable[Employee Name],"Not found"),IFERROR(INDEX(EmployeeTable[Employee Name],MATCH(I26,EmployeeTable[Employee ID],0)),"Not found")) -> Kabir Patel | K26: Processing | L26: 46249 | N26: =IF(AND(OR(K26="Pending",K26="Processing"),L26<TODAY()),"Overdue","On Track") -> Overdue
A27: ORD0024 | B27: 46260 | C27: Pioneer Supplies | D27: P004 | E27: Laptop Stand | F27: 10 | G27: 1199 | H27: =F27*G27 -> 11990 | I27: E004 | J27: =IFERROR(_xlfn.XLOOKUP(I27,EmployeeTable[Employee ID],EmployeeTable[Employee Name],"Not found"),IFERROR(INDEX(EmployeeTable[Employee Name],MATCH(I27,EmployeeTable[Employee ID],0)),"Not found")) -> Meera Singh | K27: Delivered | L27: 46268 | M27: 46267 | N27: =IF(AND(OR(K27="Pending",K27="Processing"),L27<TODAY()),"Overdue","On Track") -> On Track
A28: ORD0025 | B28: 46249 | C28: Northstar Services | D28: P005 | E28: Webcam HD | F28: 8 | G28: 2499 | H28: =F28*G28 -> 19992 | I28: E005 | J28: =IFERROR(_xlfn.XLOOKUP(I28,EmployeeTable[Employee ID],EmployeeTable[Employee Name],"Not found"),IFERROR(INDEX(EmployeeTable[Employee Name],MATCH(I28,EmployeeTable[Employee ID],0)),"Not found")) -> Ishaan Gupta | K28: Processing | L28: 46252 | N28: =IF(AND(OR(K28="Pending",K28="Processing"),L28<TODAY()),"Overdue","On Track") -> Overdue
A29: ORD0026 | B29: 46312 | C29: BluePeak Retail | D29: P006 | E29: Headset | F29: 3 | G29: 1799 | H29: =F29*G29 -> 5397 | I29: E006 | J29: =IFERROR(_xlfn.XLOOKUP(I29,EmployeeTable[Employee ID],EmployeeTable[Employee Name],"Not found"),IFERROR(INDEX(EmployeeTable[Employee Name],MATCH(I29,EmployeeTable[Employee ID],0)),"Not found")) -> Ananya Rao | K29: Processing | L29: 46319 | N29: =IF(AND(OR(K29="Pending",K29="Processing"),L29<TODAY()),"Overdue","On Track") -> On Track
A30: ORD0027 | B30: 46260 | C30: Cedar & Co. | D30: P007 | E30: Power Adapter | F30: 10 | G30: 999 | H30: =F30*G30 -> 9990 | I30: E007 | J30: =IFERROR(_xlfn.XLOOKUP(I30,EmployeeTable[Employee ID],EmployeeTable[Employee Name],"Not found"),IFERROR(INDEX(EmployeeTable[Employee Name],MATCH(I30,EmployeeTable[Employee ID],0)),"Not found")) -> Rohan Das | K30: Delivered | L30: 46263 | M30: 46264 | N30: =IF(AND(OR(K30="Pending",K30="Processing"),L30<TODAY()),"Overdue","On Track") -> On Track
A31: ORD0028 | B31: 46255 | C31: Summit Logistics | D31: P008 | E31: Notebook Pack | F31: 9 | G31: 249 | H31: =F31*G31 -> 2241 | I31: E008 | J31: =IFERROR(_xlfn.XLOOKUP(I31,EmployeeTable[Employee ID],EmployeeTable[Employee Name],"Not found"),IFERROR(INDEX(EmployeeTable[Employee Name],MATCH(I31,EmployeeTable[Employee ID],0)),"Not found")) -> Sana Khan | K31: Returned | L31: 46261 | M31: 46260 | N31: =IF(AND(OR(K31="Pending",K31="Processing"),L31<TODAY()),"Overdue","On Track") -> On Track
A32: ORD0029 | B32: 46227 | C32: Orbit Systems | D32: P009 | E32: Ethernet Cable | F32: 12 | G32: 199 | H32: =F32*G32 -> 2388 | I32: E009 | J32: =IFERROR(_xlfn.XLOOKUP(I32,EmployeeTable[Employee ID],EmployeeTable[Employee Name],"Not found"),IFERROR(INDEX(EmployeeTable[Employee Name],MATCH(I32,EmployeeTable[Employee ID],0)),"Not found")) -> Vivaan Joshi | K32: Processing | L32: 46230 | N32: =IF(AND(OR(K32="Pending",K32="Processing"),L32<TODAY()),"Overdue","On Track") -> Overdue
A33: ORD0030 | B33: 46246 | C33: MapleWorks | D33: P010 | E33: Portable SSD | F33: 5 | G33: 4999 | H33: =F33*G33 -> 24995 | I33: E010 | J33: =IFERROR(_xlfn.XLOOKUP(I33,EmployeeTable[Employee ID],EmployeeTable[Employee Name],"Not found"),IFERROR(INDEX(EmployeeTable[Employee Name],MATCH(I33,EmployeeTable[Employee ID],0)),"Not found")) -> Ira Nair | K33: Delivered | L33: 46253 | M33: 46253 | N33: =IF(AND(OR(K33="Pending",K33="Processing"),L33<TODAY()),"Overdue","On Track") -> On Track
A34: ORD0031 | B34: 46294 | C34: BrightPath Consulting | D34: P001 | E34: Wireless Mouse | F34: 8 | G34: 499 | H34: =F34*G34 -> 3992 | I34: E001 | J34: =IFERROR(_xlfn.XLOOKUP(I34,EmployeeTable[Employee ID],EmployeeTable[Employee Name],"Not found"),IFERROR(INDEX(EmployeeTable[Employee Name],MATCH(I34,EmployeeTable[Employee ID],0)),"Not found")) -> Aarav Sharma | K34: Returned | L34: 46296 | M34: 46297 | N34: =IF(AND(OR(K34="Pending",K34="Processing"),L34<TODAY()),"Overdue","On Track") -> On Track
A35: ORD0032 | B35: 46250 | C35: UrbanCart | D35: P002 | E35: Keyboard | F35: 3 | G35: 899 | H35: =F35*G35 -> 2697 | I35: E002 | J35: =IFERROR(_xlfn.XLOOKUP(I35,EmployeeTable[Employee ID],EmployeeTable[Employee Name],"Not found"),IFERROR(INDEX(EmployeeTable[Employee Name],MATCH(I35,EmployeeTable[Employee ID],0)),"Not found")) -> Diya Verma | K35: Cancelled | L35: 46260 | N35: =IF(AND(OR(K35="Pending",K35="Processing"),L35<TODAY()),"Overdue","On Track") -> On Track
A36: ORD0033 | B36: 46234 | C36: Silverline Traders | D36: P003 | E36: USB-C Hub | F36: 5 | G36: 1499 | H36: =F36*G36 -> 7495 | I36: E003 | J36: =IFERROR(_xlfn.XLOOKUP(I36,EmployeeTable[Employee ID],EmployeeTable[Employee Name],"Not found"),IFERROR(INDEX(EmployeeTable[Employee Name],MATCH(I36,EmployeeTable[Employee ID],0)),"Not found")) -> Kabir Patel | K36: Pending | L36: 46244 | N36: =IF(AND(OR(K36="Pending",K36="Processing"),L36<TODAY()),"Overdue","On Track") -> Overdue
A37: ORD0034 | B37: 46310 | C37: Nova Office Solutions | D37: P004 | E37: Laptop Stand | F37: 6 | G37: 1199 | H37: =F37*G37 -> 7194 | I37: E004 | J37: =IFERROR(_xlfn.XLOOKUP(I37,EmployeeTable[Employee ID],EmployeeTable[Employee Name],"Not found"),IFERROR(INDEX(EmployeeTable[Employee Name],MATCH(I37,EmployeeTable[Employee ID],0)),"Not found")) -> Meera Singh | K37: Pending | L37: 46317 | N37: =IF(AND(OR(K37="Pending",K37="Processing"),L37<TODAY()),"Overdue","On Track") -> On Track
A38: ORD0035 | B38: 46247 | C38: Greenfield Labs | D38: P005 | E38: Webcam HD | F38: 1 | G38: 2499 | H38: =F38*G38 -> 2499 | I38: E005 | J38: =IFERROR(_xlfn.XLOOKUP(I38,EmployeeTable[Employee ID],EmployeeTable[Employee Name],"Not found"),IFERROR(INDEX(EmployeeTable[Employee Name],MATCH(I38,EmployeeTable[Employee ID],0)),"Not found")) -> Ishaan Gupta | K38: Pending | L38: 46254 | N38: =IF(AND(OR(K38="Pending",K38="Processing"),L38<TODAY()),"Overdue","On Track") -> Overdue
A39: ORD0036 | B39: 46300 | C39: Pioneer Supplies | D39: P006 | E39: Headset | F39: 6 | G39: 1799 | H39: =F39*G39 -> 10794 | I39: E006 | J39: =IFERROR(_xlfn.XLOOKUP(I39,EmployeeTable[Employee ID],EmployeeTable[Employee Name],"Not found"),IFERROR(INDEX(EmployeeTable[Employee Name],MATCH(I39,EmployeeTable[Employee ID],0)),"Not found")) -> Ananya Rao | K39: Delivered | L39: 46306 | M39: 46305 | N39: =IF(AND(OR(K39="Pending",K39="Processing"),L39<TODAY()),"Overdue","On Track") -> On Track
A40: ORD0037 | B40: 46313 | C40: Northstar Services | D40: P007 | E40: Power Adapter | F40: 2 | G40: 999 | H40: =F40*G40 -> 1998 | I40: E007 | J40: =IFERROR(_xlfn.XLOOKUP(I40,EmployeeTable[Employee ID],EmployeeTable[Employee Name],"Not found"),IFERROR(INDEX(EmployeeTable[Employee Name],MATCH(I40,EmployeeTable[Employee ID],0)),"Not found")) -> Rohan Das | K40: Processing | L40: 46320 | N40: =IF(AND(OR(K40="Pending",K40="Processing"),L40<TODAY()),"Overdue","On Track") -> On Track
A41: ORD0038 | B41: 46306 | C41: BluePeak Retail | D41: P008 | E41: Notebook Pack | F41: 9 | G41: 249 | H41: =F41*G41 -> 2241 | I41: E008 | J41: =IFERROR(_xlfn.XLOOKUP(I41,EmployeeTable[Employee ID],EmployeeTable[Employee Name],"Not found"),IFERROR(INDEX(EmployeeTable[Employee Name],MATCH(I41,EmployeeTable[Employee ID],0)),"Not found")) -> Sana Khan | K41: Delivered | L41: 46310 | M41: 46310 | N41: =IF(AND(OR(K41="Pending",K41="Processing"),L41<TODAY()),"Overdue","On Track") -> On Track
A42: ORD0039 | B42: 46244 | C42: Cedar & Co. | D42: P009 | E42: Ethernet Cable | F42: 3 | G42: 199 | H42: =F42*G42 -> 597 | I42: E009 | J42: =IFERROR(_xlfn.XLOOKUP(I42,EmployeeTable[Employee ID],EmployeeTable[Employee Name],"Not found"),IFERROR(INDEX(EmployeeTable[Employee Name],MATCH(I42,EmployeeTable[Employee ID],0)),"Not found")) -> Vivaan Joshi | K42: Pending | L42: 46250 | N42: =IF(AND(OR(K42="Pending",K42="Processing"),L42<TODAY()),"Overdue","On Track") -> Overdue
A43: ORD0040 | B43: 46237 | C43: Summit Logistics | D43: P010 | E43: Portable SSD | F43: 7 | G43: 4999 | H43: =F43*G43 -> 34993 | I43: E010 | J43: =IFERROR(_xlfn.XLOOKUP(I43,EmployeeTable[Employee ID],EmployeeTable[Employee Name],"Not found"),IFERROR(INDEX(EmployeeTable[Employee Name],MATCH(I43,EmployeeTable[Employee ID],0)),"Not found")) -> Ira Nair | K43: Returned | L43: 46242 | M43: 46242 | N43: =IF(AND(OR(K43="Pending",K43="Processing"),L43<TODAY()),"Overdue","On Track") -> On Track
A44: ORD0041 | B44: 46275 | C44: Orbit Systems | D44: P001 | E44: Wireless Mouse | F44: 7 | G44: 499 | H44: =F44*G44 -> 3493 | I44: E001 | J44: =IFERROR(_xlfn.XLOOKUP(I44,EmployeeTable[Employee ID],EmployeeTable[Employee Name],"Not found"),IFERROR(INDEX(EmployeeTable[Employee Name],MATCH(I44,EmployeeTable[Employee ID],0)),"Not found")) -> Aarav Sharma | K44: Delivered | L44: 46282 | M44: 46283 | N44: =IF(AND(OR(K44="Pending",K44="Processing"),L44<TODAY()),"Overdue","On Track") -> On Track
A45: ORD0042 | B45: 46257 | C45: MapleWorks | D45: P002 | E45: Keyboard | F45: 2 | G45: 899 | H45: =F45*G45 -> 1798 | I45: E002 | J45: =IFERROR(_xlfn.XLOOKUP(I45,EmployeeTable[Employee ID],EmployeeTable[Employee Name],"Not found"),IFERROR(INDEX(EmployeeTable[Employee Name],MATCH(I45,EmployeeTable[Employee ID],0)),"Not found")) -> Diya Verma | K45: Delivered | L45: 46262 | M45: 46262 | N45: =IF(AND(OR(K45="Pending",K45="Processing"),L45<TODAY()),"Overdue","On Track") -> On Track
A46: ORD0043 | B46: 46312 | C46: BrightPath Consulting | D46: P003 | E46: USB-C Hub | F46: 10 | G46: 1499 | H46: =F46*G46 -> 14990 | I46: E003 | J46: =IFERROR(_xlfn.XLOOKUP(I46,EmployeeTable[Employee ID],EmployeeTable[Employee Name],"Not found"),IFERROR(INDEX(EmployeeTable[Employee Name],MATCH(I46,EmployeeTable[Employee ID],0)),"Not found")) -> Kabir Patel | K46: Delivered | L46: 46322 | M46: 46321 | N46: =IF(AND(OR(K46="Pending",K46="Processing"),L46<TODAY()),"Overdue","On Track") -> On Track
A47: ORD0044 | B47: 46314 | C47: UrbanCart | D47: P004 | E47: Laptop Stand | F47: 2 | G47: 1199 | H47: =F47*G47 -> 2398 | I47: E004 | J47: =IFERROR(_xlfn.XLOOKUP(I47,EmployeeTable[Employee ID],EmployeeTable[Employee Name],"Not found"),IFERROR(INDEX(EmployeeTable[Employee Name],MATCH(I47,EmployeeTable[Employee ID],0)),"Not found")) -> Meera Singh | K47: Delivered | L47: 46316 | M47: 46314 | N47: =IF(AND(OR(K47="Pending",K47="Processing"),L47<TODAY()),"Overdue","On Track") -> On Track
A48: ORD0045 | B48: 46272 | C48: Silverline Traders | D48: P005 | E48: Webcam HD | F48: 2 | G48: 2499 | H48: =F48*G48 -> 4998 | I48: E005 | J48: =IFERROR(_xlfn.XLOOKUP(I48,EmployeeTable[Employee ID],EmployeeTable[Employee Name],"Not found"),IFERROR(INDEX(EmployeeTable[Employee Name],MATCH(I48,EmployeeTable[Employee ID],0)),"Not found")) -> Ishaan Gupta | K48: Delivered | L48: 46282 | M48: 46284 | N48: =IF(AND(OR(K48="Pending",K48="Processing"),L48<TODAY()),"Overdue","On Track") -> On Track
A49: ORD0046 | B49: 46252 | C49: Nova Office Solutions | D49: P006 | E49: Headset | F49: 4 | G49: 1799 | H49: =F49*G49 -> 7196 | I49: E006 | J49: =IFERROR(_xlfn.XLOOKUP(I49,EmployeeTable[Employee ID],EmployeeTable[Employee Name],"Not found"),IFERROR(INDEX(EmployeeTable[Employee Name],MATCH(I49,EmployeeTable[Employee ID],0)),"Not found")) -> Ananya Rao | K49: Delivered | L49: 46262 | M49: 46263 | N49: =IF(AND(OR(K49="Pending",K49="Processing"),L49<TODAY()),"Overdue","On Track") -> On Track
A50: ORD0047 | B50: 46241 | C50: Greenfield Labs | D50: P007 | E50: Power Adapter | F50: 8 | G50: 999 | H50: =F50*G50 -> 7992 | I50: E007 | J50: =IFERROR(_xlfn.XLOOKUP(I50,EmployeeTable[Employee ID],EmployeeTable[Employee Name],"Not found"),IFERROR(INDEX(EmployeeTable[Employee Name],MATCH(I50,EmployeeTable[Employee ID],0)),"Not found")) -> Rohan Das | K50: Processing | L50: 46246 | N50: =IF(AND(OR(K50="Pending",K50="Processing"),L50<TODAY()),"Overdue","On Track") -> Overdue
A51: ORD0048 | B51: 46262 | C51: Pioneer Supplies | D51: P008 | E51: Notebook Pack | F51: 4 | G51: 249 | H51: =F51*G51 -> 996 | I51: E008 | J51: =IFERROR(_xlfn.XLOOKUP(I51,EmployeeTable[Employee ID],EmployeeTable[Employee Name],"Not found"),IFERROR(INDEX(EmployeeTable[Employee Name],MATCH(I51,EmployeeTable[Employee ID],0)),"Not found")) -> Sana Khan | K51: Delivered | L51: 46265 | M51: 46265 | N51: =IF(AND(OR(K51="Pending",K51="Processing"),L51<TODAY()),"Overdue","On Track") -> On Track
A52: ORD0049 | B52: 46269 | C52: Northstar Services | D52: P009 | E52: Ethernet Cable | F52: 7 | G52: 199 | H52: =F52*G52 -> 1393 | I52: E009 | J52: =IFERROR(_xlfn.XLOOKUP(I52,EmployeeTable[Employee ID],EmployeeTable[Employee Name],"Not found"),IFERROR(INDEX(EmployeeTable[Employee Name],MATCH(I52,EmployeeTable[Employee ID],0)),"Not found")) -> Vivaan Joshi | K52: Delivered | L52: 46277 | M52: 46279 | N52: =IF(AND(OR(K52="Pending",K52="Processing"),L52<TODAY()),"Overdue","On Track") -> On Track
A53: ORD0050 | B53: 46308 | C53: BluePeak Retail | D53: P010 | E53: Portable SSD | F53: 11 | G53: 4999 | H53: =F53*G53 -> 54989 | I53: E010 | J53: =IFERROR(_xlfn.XLOOKUP(I53,EmployeeTable[Employee ID],EmployeeTable[Employee Name],"Not found"),IFERROR(INDEX(EmployeeTable[Employee Name],MATCH(I53,EmployeeTable[Employee ID],0)),"Not found")) -> Ira Nair | K53: Delivered | L53: 46311 | M53: 46313 | N53: =IF(AND(OR(K53="Pending",K53="Processing"),L53<TODAY()),"Overdue","On Track") -> On Track
A54: ORD0051 | B54: 46271 | C54: Cedar & Co. | D54: P001 | E54: Wireless Mouse | F54: 2 | G54: 499 | H54: =F54*G54 -> 998 | I54: E001 | J54: =IFERROR(_xlfn.XLOOKUP(I54,EmployeeTable[Employee ID],EmployeeTable[Employee Name],"Not found"),IFERROR(INDEX(EmployeeTable[Employee Name],MATCH(I54,EmployeeTable[Employee ID],0)),"Not found")) -> Aarav Sharma | K54: Delivered | L54: 46276 | M54: 46277 | N54: =IF(AND(OR(K54="Pending",K54="Processing"),L54<TODAY()),"Overdue","On Track") -> On Track
A55: ORD0052 | B55: 46257 | C55: Summit Logistics | D55: P002 | E55: Keyboard | F55: 3 | G55: 899 | H55: =F55*G55 -> 2697 | I55: E002 | J55: =IFERROR(_xlfn.XLOOKUP(I55,EmployeeTable[Employee ID],EmployeeTable[Employee Name],"Not found"),IFERROR(INDEX(EmployeeTable[Employee Name],MATCH(I55,EmployeeTable[Employee ID],0)),"Not found")) -> Diya Verma | K55: Delivered | L55: 46265 | M55: 46265 | N55: =IF(AND(OR(K55="Pending",K55="Processing"),L55<TODAY()),"Overdue","On Track") -> On Track
A56: ORD0053 | B56: 46311 | C56: Orbit Systems | D56: P003 | E56: USB-C Hub | F56: 2 | G56: 1499 | H56: =F56*G56 -> 2998 | I56: E003 | J56: =IFERROR(_xlfn.XLOOKUP(I56,EmployeeTable[Employee ID],EmployeeTable[Employee Name],"Not found"),IFERROR(INDEX(EmployeeTable[Employee Name],MATCH(I56,EmployeeTable[Employee ID],0)),"Not found")) -> Kabir Patel | K56: Processing | L56: 46318 | N56: =IF(AND(OR(K56="Pending",K56="Processing"),L56<TODAY()),"Overdue","On Track") -> On Track
A57: ORD0054 | B57: 46244 | C57: MapleWorks | D57: P004 | E57: Laptop Stand | F57: 2 | G57: 1199 | H57: =F57*G57 -> 2398 | I57: E004 | J57: =IFERROR(_xlfn.XLOOKUP(I57,EmployeeTable[Employee ID],EmployeeTable[Employee Name],"Not found"),IFERROR(INDEX(EmployeeTable[Employee Name],MATCH(I57,EmployeeTable[Employee ID],0)),"Not found")) -> Meera Singh | K57: Pending | L57: 46246 | N57: =IF(AND(OR(K57="Pending",K57="Processing"),L57<TODAY()),"Overdue","On Track") -> Overdue
A58: ORD0055 | B58: 46245 | C58: BrightPath Consulting | D58: P005 | E58: Webcam HD | F58: 1 | G58: 2499 | H58: =F58*G58 -> 2499 | I58: E005 | J58: =IFERROR(_xlfn.XLOOKUP(I58,EmployeeTable[Employee ID],EmployeeTable[Employee Name],"Not found"),IFERROR(INDEX(EmployeeTable[Employee Name],MATCH(I58,EmployeeTable[Employee ID],0)),"Not found")) -> Ishaan Gupta | K58: Returned | L58: 46248 | M58: 46248 | N58: =IF(AND(OR(K58="Pending",K58="Processing"),L58<TODAY()),"Overdue","On Track") -> On Track
A59: ORD0056 | B59: 46293 | C59: UrbanCart | D59: P006 | E59: Headset | F59: 7 | G59: 1799 | H59: =F59*G59 -> 12593 | I59: E006 | J59: =IFERROR(_xlfn.XLOOKUP(I59,EmployeeTable[Employee ID],EmployeeTable[Employee Name],"Not found"),IFERROR(INDEX(EmployeeTable[Employee Name],MATCH(I59,EmployeeTable[Employee ID],0)),"Not found")) -> Ananya Rao | K59: Pending | L59: 46302 | N59: =IF(AND(OR(K59="Pending",K59="Processing"),L59<TODAY()),"Overdue","On Track") -> Overdue
A60: ORD0057 | B60: 46263 | C60: Silverline Traders | D60: P007 | E60: Power Adapter | F60: 1 | G60: 999 | H60: =F60*G60 -> 999 | I60: E007 | J60: =IFERROR(_xlfn.XLOOKUP(I60,EmployeeTable[Employee ID],EmployeeTable[Employee Name],"Not found"),IFERROR(INDEX(EmployeeTable[Employee Name],MATCH(I60,EmployeeTable[Employee ID],0)),"Not found")) -> Rohan Das | K60: Delivered | L60: 46267 | M60: 46267 | N60: =IF(AND(OR(K60="Pending",K60="Processing"),L60<TODAY()),"Overdue","On Track") -> On Track
A61: ORD0058 | B61: 46281 | C61: Nova Office Solutions | D61: P008 | E61: Notebook Pack | F61: 8 | G61: 249 | H61: =F61*G61 -> 1992 | I61: E008 | J61: =IFERROR(_xlfn.XLOOKUP(I61,EmployeeTable[Employee ID],EmployeeTable[Employee Name],"Not found"),IFERROR(INDEX(EmployeeTable[Employee Name],MATCH(I61,EmployeeTable[Employee ID],0)),"Not found")) -> Sana Khan | K61: Delivered | L61: 46287 | M61: 46289 | N61: =IF(AND(OR(K61="Pending",K61="Processing"),L61<TODAY()),"Overdue","On Track") -> On Track
A62: ORD0059 | B62: 46243 | C62: Greenfield Labs | D62: P009 | E62: Ethernet Cable | F62: 11 | G62: 199 | H62: =F62*G62 -> 2189 | I62: E009 | J62: =IFERROR(_xlfn.XLOOKUP(I62,EmployeeTable[Employee ID],EmployeeTable[Employee Name],"Not found"),IFERROR(INDEX(EmployeeTable[Employee Name],MATCH(I62,EmployeeTable[Employee ID],0)),"Not found")) -> Vivaan Joshi | K62: Delivered | L62: 46252 | M62: 46252 | N62: =IF(AND(OR(K62="Pending",K62="Processing"),L62<TODAY()),"Overdue","On Track") -> On Track
A63: ORD0060 | B63: 46287 | C63: Pioneer Supplies | D63: P010 | E63: Portable SSD | F63: 1 | G63: 4999 | H63: =F63*G63 -> 4999 | I63: E010 | J63: =IFERROR(_xlfn.XLOOKUP(I63,EmployeeTable[Employee ID],EmployeeTable[Employee Name],"Not found"),IFERROR(INDEX(EmployeeTable[Employee Name],MATCH(I63,EmployeeTable[Employee ID],0)),"Not found")) -> Ira Nair | K63: Delivered | L63: 46297 | M63: 46297 | N63: =IF(AND(OR(K63="Pending",K63="Processing"),L63<TODAY()),"Overdue","On Track") -> On Track

Sheet Inventory Management
A1: Inventory Management
A2: Automated stock balances, Indian Rupee (₹) valuation, reorder threshold alerts, and stock level visualization
A3: Product ID | B3: Product Name | C3: Category | D3: Opening Stock | E3: Stock Received | F3: Stock Issued | G3: Current Stock | H3: Reorder Level | I3: Unit Cost (₹) | J3: Inventory Value (₹) | K3: Reorder Alert | M3: Data Quality & Summary | N3: Status / Value
A4: P001 | B4: Wireless Mouse | C4: Accessories | D4: 120 | E4: 24 | F4: 25 | G4: =D4 + E4 - F4 -> 119 | H4: 35 | I4: 499 | J4: =MAX(G4,0)*I4 -> 59381 | K4: =IF(G4<H4,"REORDER","OK") -> OK | M4: Duplicate Product IDs | N4: =IF(SUMPRODUCT(--(COUNTIF(InventoryTable[Product ID],InventoryTable[Product ID])>1))>0,"DUPLICATES FOUND","IDs unique") -> IDs unique
A5: P002 | B5: Keyboard | C5: Accessories | D5: 80 | E5: 30 | F5: 107 | G5: =D5 + E5 - F5 -> 3 | H5: 25 | I5: 899 | J5: =MAX(G5,0)*I5 -> 2697 | K5: =IF(G5<H5,"REORDER","OK") -> REORDER | M5: Missing Product Names | N5: =IF(COUNTBLANK(InventoryTable[Product Name])>0,"MISSING VALUES","Complete") -> Complete
A6: P003 | B6: USB-C Hub | C6: Accessories | D6: 55 | E6: 52 | F6: 77 | G6: =D6 + E6 - F6 -> 30 | H6: 18 | I6: 1499 | J6: =MAX(G6,0)*I6 -> 44970 | K6: =IF(G6<H6,"REORDER","OK") -> OK | M6: Negative Stock Check | N6: =IF(COUNTIF(InventoryTable[Current Stock],"<0")>0,"NEGATIVE STOCK","All Non-Negative") -> All Non-Negative
A7: P004 | B7: Laptop Stand | C7: Office Supplies | D7: 70 | E7: 30 | F7: 88 | G7: =D7 + E7 - F7 -> 12 | H7: 20 | I7: 1199 | J7: =MAX(G7,0)*I7 -> 14388 | K7: =IF(G7<H7,"REORDER","OK") -> REORDER | M7: Total SKUs Tracked | N7: =COUNTA(InventoryTable[Product ID]) -> 10
A8: P005 | B8: Webcam HD | C8: Electronics | D8: 40 | E8: 60 | F8: 97 | G8: =D8 + E8 - F8 -> 3 | H8: 15 | I8: 2499 | J8: =MAX(G8,0)*I8 -> 7497 | K8: =IF(G8<H8,"REORDER","OK") -> REORDER | M8: Total Current Units | N8: =SUM(InventoryTable[Current Stock]) -> 585
A9: P006 | B9: Headset | C9: Electronics | D9: 65 | E9: 62 | F9: 72 | G9: =D9 + E9 - F9 -> 55 | H9: 20 | I9: 1799 | J9: =MAX(G9,0)*I9 -> 98945 | K9: =IF(G9<H9,"REORDER","OK") -> OK | M9: Items Below Reorder | N9: =COUNTIF(InventoryTable[Reorder Alert],"REORDER") -> 4
A10: P007 | B10: Power Adapter | C10: Electronics | D10: 90 | E10: 2 | F10: 26 | G10: =D10 + E10 - F10 -> 66 | H10: 30 | I10: 999 | J10: =MAX(G10,0)*I10 -> 65934 | K10: =IF(G10<H10,"REORDER","OK") -> OK | M10: Total Inventory Value | N10: =SUM(InventoryTable[Inventory Value (₹)]) -> 384115
A11: P008 | B11: Notebook Pack | C11: Office Supplies | D11: 150 | E11: 37 | F11: 43 | G11: =D11 + E11 - F11 -> 144 | H11: 40 | I11: 249 | J11: =MAX(G11,0)*I11 -> 35856 | K11: =IF(G11<H11,"REORDER","OK") -> OK
A12: P009 | B12: Ethernet Cable | C12: Networking | D12: 200 | E12: 51 | F12: 103 | G12: =D12 + E12 - F12 -> 148 | H12: 60 | I12: 199 | J12: =MAX(G12,0)*I12 -> 29452 | K12: =IF(G12<H12,"REORDER","OK") -> OK
A13: P010 | B13: Portable SSD | C13: Storage | D13: 28 | E13: 31 | F13: 54 | G13: =D13 + E13 - F13 -> 5 | H13: 12 | I13: 4999 | J13: =MAX(G13,0)*I13 -> 24995 | K13: =IF(G13<H13,"REORDER","OK") -> REORDER

Sheet Employee Master
A1: Employee Master
A2: Employee directory, dynamic tenure calculation, VLOOKUP/XLOOKUP demonstrations, and ID integrity checks
A3: Employee ID | B3: Employee Name | C3: Department | D3: Designation | E3: Joining Date | F3: Tenure (Years) | G3: Employee Status | I3: Lookup Demonstration (VLOOKUP & XLOOKUP)
A4: E001 | B4: Aarav Sharma | C4: Operations | D4: MIS Executive | E4: 44970 | F4: =YEARFRAC(E4,TODAY()) -> 3.6833333 | G4: Active | I4: Lookup Employee ID (Input) | J4: E003
A5: E002 | B5: Diya Verma | C5: Field Operations | D5: Field Coordinator | E5: 44746 | F5: =YEARFRAC(E5,TODAY()) -> 4.2916667 | G5: Active | I5: VLOOKUP Employee Name | J5: =VLOOKUP(J4,EmployeeTable[[Employee ID]:[Employee Name]],2,FALSE()) -> Kabir Patel
A6: E003 | B6: Kabir Patel | C6: Warehouse | D6: Inventory Analyst | E6: 45306 | F6: =YEARFRAC(E6,TODAY()) -> 2.7611111 | G6: Active | I6: XLOOKUP Department | J6: =IFERROR(_xlfn.XLOOKUP(J4,EmployeeTable[Employee ID],EmployeeTable[Department],"Not found"),IFERROR(INDEX(EmployeeTable[Department],MATCH(J4,EmployeeTable[Employee ID],0)),"Not found")) -> Warehouse
A7: E004 | B7: Meera Singh | C7: Customer Service | D7: Operations Executive | E7: 44508 | F7: =YEARFRAC(E7,TODAY()) -> 4.9472222 | G7: Active | I7: XLOOKUP Designation | J7: =IFERROR(_xlfn.XLOOKUP(J4,EmployeeTable[Employee ID],EmployeeTable[Designation],"Not found"),IFERROR(INDEX(EmployeeTable[Designation],MATCH(J4,EmployeeTable[Employee ID],0)),"Not found")) -> Inventory Analyst
A8: E005 | B8: Ishaan Gupta | C8: Field Operations | D8: Field Executive | E8: 45159 | F8: =YEARFRAC(E8,TODAY()) -> 3.1611111 | G8: Active
A9: E006 | B9: Ananya Rao | C9: Operations | D9: MIS Analyst | E9: 44621 | F9: =YEARFRAC(E9,TODAY()) -> 4.6333333 | G9: Active | I9: Employee Data Quality Audit
A10: E007 | B10: Rohan Das | C10: Warehouse | D10: Store Executive | E10: 45418 | F10: =YEARFRAC(E10,TODAY()) -> 2.4527778 | G10: Active | I10: Duplicate ID Check | J10: =IF(SUMPRODUCT(--(COUNTIF(EmployeeTable[Employee ID],EmployeeTable[Employee ID])>1))>0,"DUPLICATE FOUND","IDs unique") -> IDs unique
A11: E008 | B11: Sana Khan | C11: Customer Service | D11: Order Coordinator | E11: 45201 | F11: =YEARFRAC(E11,TODAY()) -> 3.0472222 | G11: Active | I11: Missing Name Check | J11: =IF(COUNTBLANK(EmployeeTable[Employee Name])>0,"MISSING VALUES","Complete") -> Complete
A12: E009 | B12: Vivaan Joshi | C12: Field Operations | D12: Field Executive | E12: 43999 | F12: =YEARFRAC(E12,TODAY()) -> 6.3388889 | G12: Active
A13: E010 | B13: Ira Nair | C13: Operations | D13: Team Lead | E13: 43731 | F13: =YEARFRAC(E13,TODAY()) -> 7.0722222 | G13: Active

Sheet Daily MIS Report
A1: Daily MIS Report — Operational Snapshot
A2: Daily operational metrics • Set Period Start and Period End to the same day for a single-day view
A4: Period Start | B4: =TODAY() -> 46314 | D4: Edit yellow Period Start (B4) and Period End (B5) cells to recalculate all report metrics and charts for any custom reporting window.
A5: Period End | B5: =TODAY() -> 46314
E6: Inventory Exceptions Watchlist (Products Below Reorder Level)
A7: Operational Metric | B7: Period Result | C7: Domain | E7: Product ID | F7: Product Name | G7: Current Stock | H7: Reorder Level | I7: Alert Status
A8: Orders created | B8: =COUNTIFS(OrdersTable[Order Date],">="&$B$4,OrdersTable[Order Date],"<"&$B$5+1) -> 1 | C8: Orders | E8: ='Inventory Management'!A5 -> P002 | F8: ='Inventory Management'!B5 -> Keyboard | G8: ='Inventory Management'!G5 -> 3 | H8: ='Inventory Management'!H5 -> 25 | I8: ='Inventory Management'!K5 -> REORDER
A9: Delivered orders | B9: =COUNTIFS(OrdersTable[Actual Delivery],">="&$B$4,OrdersTable[Actual Delivery],"<"&$B$5+1) -> 2 | C9: Orders | E9: ='Inventory Management'!A7 -> P004 | F9: ='Inventory Management'!B7 -> Laptop Stand | G9: ='Inventory Management'!G7 -> 12 | H9: ='Inventory Management'!H7 -> 20 | I9: ='Inventory Management'!K7 -> REORDER
A10: Field activities assigned | B10: =COUNTIFS(FMSTable[Activity Date],">="&$B$4,FMSTable[Activity Date],"<"&$B$5+1) -> 2 | C10: Field Ops | E10: ='Inventory Management'!A8 -> P005 | F10: ='Inventory Management'!B8 -> Webcam HD | G10: ='Inventory Management'!G8 -> 3 | H10: ='Inventory Management'!H8 -> 15 | I10: ='Inventory Management'!K8 -> REORDER
A11: Field activities completed | B11: =COUNTIFS(FMSTable[Activity Date],">="&$B$4,FMSTable[Activity Date],"<"&$B$5+1,FMSTable[Status],"Completed") -> 2 | C11: Field Ops | E11: ='Inventory Management'!A13 -> P010 | F11: ='Inventory Management'!B13 -> Portable SSD | G11: ='Inventory Management'!G13 -> 5 | H11: ='Inventory Management'!H13 -> 12 | I11: ='Inventory Management'!K13 -> REORDER
A12: Checklist tasks due | B12: =COUNTIFS(ChecklistTable[Due Date],">="&$B$4,ChecklistTable[Due Date],"<"&$B$5+1) -> 1 | C12: Checklist
A13: On-time checklist completions | B13: =COUNTIFS(ChecklistTable[Completion Date],">="&$B$4,ChecklistTable[Completion Date],"<"&$B$5+1,ChecklistTable[Compliance Status],"On Time") -> 1 | C13: Checklist
A14: Low-stock products (Reorder) | B14: =COUNTIF(InventoryTable[Reorder Alert],"REORDER") -> 4 | C14: Inventory
A15: Order value (₹) | B15: =SUMIFS(OrdersTable[Order Value (₹)],OrdersTable[Order Date],">="&$B$4,OrdersTable[Order Date],"<"&$B$5+1) -> 2398 | C15: Revenue
A16: Current inventory value (₹) | B16: =SUM(InventoryTable[Inventory Value (₹)]) -> 384115 | C16: Inventory

Sheet Weekly MIS Report
A1: Weekly MIS Report — Monday to Sunday Operational Summary
A2: Weekly operational metrics • Defaults to Monday–Sunday of the current week; edit yellow cells for historical weeks
A4: Period Start | B4: =TODAY()-WEEKDAY(TODAY(),2)+1 -> 46314 | D4: Edit yellow Period Start (B4) and Period End (B5) cells to recalculate all report metrics and charts for any custom reporting window.
A5: Period End | B5: =TODAY()-WEEKDAY(TODAY(),2)+7 -> 46320
E6: Inventory Exceptions Watchlist (Products Below Reorder Level)
A7: Operational Metric | B7: Period Result | C7: Domain | E7: Product ID | F7: Product Name | G7: Current Stock | H7: Reorder Level | I7: Alert Status
A8: Orders created | B8: =COUNTIFS(OrdersTable[Order Date],">="&$B$4,OrdersTable[Order Date],"<"&$B$5+1) -> 1 | C8: Orders | E8: ='Inventory Management'!A5 -> P002 | F8: ='Inventory Management'!B5 -> Keyboard | G8: ='Inventory Management'!G5 -> 3 | H8: ='Inventory Management'!H5 -> 25 | I8: ='Inventory Management'!K5 -> REORDER
A9: Delivered orders | B9: =COUNTIFS(OrdersTable[Actual Delivery],">="&$B$4,OrdersTable[Actual Delivery],"<"&$B$5+1) -> 2 | C9: Orders | E9: ='Inventory Management'!A7 -> P004 | F9: ='Inventory Management'!B7 -> Laptop Stand | G9: ='Inventory Management'!G7 -> 12 | H9: ='Inventory Management'!H7 -> 20 | I9: ='Inventory Management'!K7 -> REORDER
A10: Field activities assigned | B10: =COUNTIFS(FMSTable[Activity Date],">="&$B$4,FMSTable[Activity Date],"<"&$B$5+1) -> 2 | C10: Field Ops | E10: ='Inventory Management'!A8 -> P005 | F10: ='Inventory Management'!B8 -> Webcam HD | G10: ='Inventory Management'!G8 -> 3 | H10: ='Inventory Management'!H8 -> 15 | I10: ='Inventory Management'!K8 -> REORDER
A11: Field activities completed | B11: =COUNTIFS(FMSTable[Activity Date],">="&$B$4,FMSTable[Activity Date],"<"&$B$5+1,FMSTable[Status],"Completed") -> 2 | C11: Field Ops | E11: ='Inventory Management'!A13 -> P010 | F11: ='Inventory Management'!B13 -> Portable SSD | G11: ='Inventory Management'!G13 -> 5 | H11: ='Inventory Management'!H13 -> 12 | I11: ='Inventory Management'!K13 -> REORDER
A12: Checklist tasks due | B12: =COUNTIFS(ChecklistTable[Due Date],">="&$B$4,ChecklistTable[Due Date],"<"&$B$5+1) -> 13 | C12: Checklist
A13: On-time checklist completions | B13: =COUNTIFS(ChecklistTable[Completion Date],">="&$B$4,ChecklistTable[Completion Date],"<"&$B$5+1,ChecklistTable[Compliance Status],"On Time") -> 2 | C13: Checklist
A14: Low-stock products (Reorder) | B14: =COUNTIF(InventoryTable[Reorder Alert],"REORDER") -> 4 | C14: Inventory
A15: Order value (₹) | B15: =SUMIFS(OrdersTable[Order Value (₹)],OrdersTable[Order Date],">="&$B$4,OrdersTable[Order Date],"<"&$B$5+1) -> 2398 | C15: Revenue
A16: Current inventory value (₹) | B16: =SUM(InventoryTable[Inventory Value (₹)]) -> 384115 | C16: Inventory

Sheet Monthly MIS Report
A1: Monthly MIS Report — Full Calendar Month Performance
A2: Monthly operational metrics • Defaults to the current calendar month; edit yellow cells for historical months
A4: Period Start | B4: =DATE(YEAR(TODAY()),MONTH(TODAY()),1) -> 46296 | D4: Edit yellow Period Start (B4) and Period End (B5) cells to recalculate all report metrics and charts for any custom reporting window.
A5: Period End | B5: =EOMONTH(TODAY(),0) -> 46326
E6: Inventory Exceptions Watchlist (Products Below Reorder Level)
A7: Operational Metric | B7: Period Result | C7: Domain | E7: Product ID | F7: Product Name | G7: Current Stock | H7: Reorder Level | I7: Alert Status
A8: Orders created | B8: =COUNTIFS(OrdersTable[Order Date],">="&$B$4,OrdersTable[Order Date],"<"&$B$5+1) -> 16 | C8: Orders | E8: ='Inventory Management'!A5 -> P002 | F8: ='Inventory Management'!B5 -> Keyboard | G8: ='Inventory Management'!G5 -> 3 | H8: ='Inventory Management'!H5 -> 25 | I8: ='Inventory Management'!K5 -> REORDER
A9: Delivered orders | B9: =COUNTIFS(OrdersTable[Actual Delivery],">="&$B$4,OrdersTable[Actual Delivery],"<"&$B$5+1) -> 11 | C9: Orders | E9: ='Inventory Management'!A7 -> P004 | F9: ='Inventory Management'!B7 -> Laptop Stand | G9: ='Inventory Management'!G7 -> 12 | H9: ='Inventory Management'!H7 -> 20 | I9: ='Inventory Management'!K7 -> REORDER
A10: Field activities assigned | B10: =COUNTIFS(FMSTable[Activity Date],">="&$B$4,FMSTable[Activity Date],"<"&$B$5+1) -> 19 | C10: Field Ops | E10: ='Inventory Management'!A8 -> P005 | F10: ='Inventory Management'!B8 -> Webcam HD | G10: ='Inventory Management'!G8 -> 3 | H10: ='Inventory Management'!H8 -> 15 | I10: ='Inventory Management'!K8 -> REORDER
A11: Field activities completed | B11: =COUNTIFS(FMSTable[Activity Date],">="&$B$4,FMSTable[Activity Date],"<"&$B$5+1,FMSTable[Status],"Completed") -> 13 | C11: Field Ops | E11: ='Inventory Management'!A13 -> P010 | F11: ='Inventory Management'!B13 -> Portable SSD | G11: ='Inventory Management'!G13 -> 5 | H11: ='Inventory Management'!H13 -> 12 | I11: ='Inventory Management'!K13 -> REORDER
A12: Checklist tasks due | B12: =COUNTIFS(ChecklistTable[Due Date],">="&$B$4,ChecklistTable[Due Date],"<"&$B$5+1) -> 35 | C12: Checklist
A13: On-time checklist completions | B13: =COUNTIFS(ChecklistTable[Completion Date],">="&$B$4,ChecklistTable[Completion Date],"<"&$B$5+1,ChecklistTable[Compliance Status],"On Time") -> 14 | C13: Checklist
A14: Low-stock products (Reorder) | B14: =COUNTIF(InventoryTable[Reorder Alert],"REORDER") -> 4 | C14: Inventory
A15: Order value (₹) | B15: =SUMIFS(OrdersTable[Order Value (₹)],OrdersTable[Order Date],">="&$B$4,OrdersTable[Order Date],"<"&$B$5+1) -> 116281 | C15: Revenue
A16: Current inventory value (₹) | B16: =SUM(InventoryTable[Inventory Value (₹)]) -> 384115 | C16: Inventory

Sheet Raw Data
A1: Raw Data — Operational Registers
A2: Left: FMS Field Activities (FMSTable) • Center: Checklist Compliance Register (ChecklistTable) • Right: Data Quality Audit
A3: FMS / Field Activities Register (FMSTable) | L3: Checklist Tasks Register (ChecklistTable) | W3: Data Quality Audit
A4: Activity ID | B4: Activity Date | C4: Employee ID | D4: Employee Name (XLOOKUP) | E4: Activity Type | F4: Assignment Date/Time | G4: Completion Date/Time | H4: Status | I4: TAT (Hours) | J4: SLA Result | L4: Task ID | M4: Employee ID | N4: Employee Name (XLOOKUP) | O4: Task Type | P4: Assigned Date | Q4: Due Date | R4: Completion Date | S4: Task Status | T4: Compliance Status | U4: On-Time Flag | W4: Check Metric | X4: Validation Result
A5: FMS0001 | B5: 46311 | C5: E004 | D5: =IFERROR(_xlfn.XLOOKUP(C5,EmployeeTable[Employee ID],EmployeeTable[Employee Name],"Not found"),IFERROR(INDEX(EmployeeTable[Employee Name],MATCH(C5,EmployeeTable[Employee ID],0)),"Not found")) -> Meera Singh | E5: Site Visit | F5: 46311.365 | G5: 46311.906 | H5: Completed | I5: =IF(G5="","",(G5-F5)*24) -> 13 | J5: =IF(H5="Completed",IF(I5<=4,"Within SLA","Delayed"),"") -> Delayed | L5: TASK0001 | M5: E008 | N5: =IFERROR(_xlfn.XLOOKUP(M5,EmployeeTable[Employee ID],EmployeeTable[Employee Name],"Not found"),IFERROR(INDEX(EmployeeTable[Employee Name],MATCH(M5,EmployeeTable[Employee ID],0)),"Not found")) -> Sana Khan | O5: Opening Checklist | P5: 46271 | Q5: 46272 | R5: 46274 | S5: Completed | T5: =IF(S5="Completed",IF(R5<=Q5,"On Time","Delayed"),IF(Q5<TODAY(),"Overdue","Pending")) -> Delayed | U5: =IF(S5="Completed",IF(R5<=Q5,1,0),0) -> 0 | W5: Duplicate Activity IDs | X5: =IF(SUMPRODUCT(--(COUNTIF(FMSTable[Activity ID],FMSTable[Activity ID])>1))>0,"DUPLICATES FOUND","IDs unique") -> IDs unique
A6: FMS0002 | B6: 46281 | C6: E007 | D6: =IFERROR(_xlfn.XLOOKUP(C6,EmployeeTable[Employee ID],EmployeeTable[Employee Name],"Not found"),IFERROR(INDEX(EmployeeTable[Employee Name],MATCH(C6,EmployeeTable[Employee ID],0)),"Not found")) -> Rohan Das | E6: Stock Audit | F6: 46281.417 | H6: Cancelled | I6: =IF(G6="","",(G6-F6)*24) | J6: =IF(H6="Completed",IF(I6<=4,"Within SLA","Delayed"),"") | L6: TASK0002 | M6: E005 | N6: =IFERROR(_xlfn.XLOOKUP(M6,EmployeeTable[Employee ID],EmployeeTable[Employee Name],"Not found"),IFERROR(INDEX(EmployeeTable[Employee Name],MATCH(M6,EmployeeTable[Employee ID],0)),"Not found")) -> Ishaan Gupta | O6: Safety Inspection | P6: 46304 | Q6: 46309 | R6: 46310 | S6: Completed | T6: =IF(S6="Completed",IF(R6<=Q6,"On Time","Delayed"),IF(Q6<TODAY(),"Overdue","Pending")) -> Delayed | U6: =IF(S6="Completed",IF(R6<=Q6,1,0),0) -> 0 | W6: Missing Activity IDs | X6: =IF(COUNTBLANK(FMSTable[Activity ID])>0,"MISSING VALUES","Complete") -> Complete
A7: FMS0003 | B7: 46309 | C7: E010 | D7: =IFERROR(_xlfn.XLOOKUP(C7,EmployeeTable[Employee ID],EmployeeTable[Employee Name],"Not found"),IFERROR(INDEX(EmployeeTable[Employee Name],MATCH(C7,EmployeeTable[Employee ID],0)),"Not found")) -> Ira Nair | E7: Customer Follow-up | F7: 46309.885 | G7: 46309.938 | H7: Completed | I7: =IF(G7="","",(G7-F7)*24) -> 1.25 | J7: =IF(H7="Completed",IF(I7<=4,"Within SLA","Delayed"),"") -> Within SLA | L7: TASK0003 | M7: E002 | N7: =IFERROR(_xlfn.XLOOKUP(M7,EmployeeTable[Employee ID],EmployeeTable[Employee Name],"Not found"),IFERROR(INDEX(EmployeeTable[Employee Name],MATCH(M7,EmployeeTable[Employee ID],0)),"Not found")) -> Diya Verma | O7: Stock Reconciliation | P7: 46272 | Q7: 46277 | R7: 46275 | S7: Completed | T7: =IF(S7="Completed",IF(R7<=Q7,"On Time","Delayed"),IF(Q7<TODAY(),"Overdue","Pending")) -> On Time | U7: =IF(S7="Completed",IF(R7<=Q7,1,0),0) -> 1 | W7: Duplicate Task IDs | X7: =IF(SUMPRODUCT(--(COUNTIF(ChecklistTable[Task ID],ChecklistTable[Task ID])>1))>0,"DUPLICATES FOUND","IDs unique") -> IDs unique
A8: FMS0004 | B8: 46271 | C8: E003 | D8: =IFERROR(_xlfn.XLOOKUP(C8,EmployeeTable[Employee ID],EmployeeTable[Employee Name],"Not found"),IFERROR(INDEX(EmployeeTable[Employee Name],MATCH(C8,EmployeeTable[Employee ID],0)),"Not found")) -> Kabir Patel | E8: Delivery Verification | F8: 46271.885 | G8: 46272.219 | H8: Completed | I8: =IF(G8="","",(G8-F8)*24) -> 8 | J8: =IF(H8="Completed",IF(I8<=4,"Within SLA","Delayed"),"") -> Delayed | L8: TASK0004 | M8: E009 | N8: =IFERROR(_xlfn.XLOOKUP(M8,EmployeeTable[Employee ID],EmployeeTable[Employee Name],"Not found"),IFERROR(INDEX(EmployeeTable[Employee Name],MATCH(M8,EmployeeTable[Employee ID],0)),"Not found")) -> Vivaan Joshi | O8: Customer Callback | P8: 46299 | Q8: 46304 | R8: 46303 | S8: Completed | T8: =IF(S8="Completed",IF(R8<=Q8,"On Time","Delayed"),IF(Q8<TODAY(),"Overdue","Pending")) -> On Time | U8: =IF(S8="Completed",IF(R8<=Q8,1,0),0) -> 1 | W8: Missing Task IDs | X8: =IF(COUNTBLANK(ChecklistTable[Task ID])>0,"MISSING VALUES","Complete") -> Complete
A9: FMS0005 | B9: 46299 | C9: E006 | D9: =IFERROR(_xlfn.XLOOKUP(C9,EmployeeTable[Employee ID],EmployeeTable[Employee Name],"Not found"),IFERROR(INDEX(EmployeeTable[Employee Name],MATCH(C9,EmployeeTable[Employee ID],0)),"Not found")) -> Ananya Rao | E9: Document Collection | F9: 46299.708 | G9: 46299.917 | H9: Completed | I9: =IF(G9="","",(G9-F9)*24) -> 5 | J9: =IF(H9="Completed",IF(I9<=4,"Within SLA","Delayed"),"") -> Delayed | L9: TASK0005 | M9: E006 | N9: =IFERROR(_xlfn.XLOOKUP(M9,EmployeeTable[Employee ID],EmployeeTable[Employee Name],"Not found"),IFERROR(INDEX(EmployeeTable[Employee Name],MATCH(M9,EmployeeTable[Employee ID],0)),"Not found")) -> Ananya Rao | O9: Document Review | P9: 46305 | Q9: 46305 | R9: 46305 | S9: Completed | T9: =IF(S9="Completed",IF(R9<=Q9,"On Time","Delayed"),IF(Q9<TODAY(),"Overdue","Pending")) -> On Time | U9: =IF(S9="Completed",IF(R9<=Q9,1,0),0) -> 1 | W9: Total FMS Records | X9: =COUNTA(FMSTable[Activity ID]) -> 50
A10: FMS0006 | B10: 46272 | C10: E009 | D10: =IFERROR(_xlfn.XLOOKUP(C10,EmployeeTable[Employee ID],EmployeeTable[Employee Name],"Not found"),IFERROR(INDEX(EmployeeTable[Employee Name],MATCH(C10,EmployeeTable[Employee ID],0)),"Not found")) -> Vivaan Joshi | E10: Quality Check | F10: 46272.729 | H10: In Progress | I10: =IF(G10="","",(G10-F10)*24) | J10: =IF(H10="Completed",IF(I10<=4,"Within SLA","Delayed"),"") | L10: TASK0006 | M10: E003 | N10: =IFERROR(_xlfn.XLOOKUP(M10,EmployeeTable[Employee ID],EmployeeTable[Employee Name],"Not found"),IFERROR(INDEX(EmployeeTable[Employee Name],MATCH(M10,EmployeeTable[Employee ID],0)),"Not found")) -> Kabir Patel | O10: End-of-Day Closure | P10: 46275 | Q10: 46275 | R10: 46277 | S10: Completed | T10: =IF(S10="Completed",IF(R10<=Q10,"On Time","Delayed"),IF(Q10<TODAY(),"Overdue","Pending")) -> Delayed | U10: =IF(S10="Completed",IF(R10<=Q10,1,0),0) -> 0 | W10: Total Checklist Tasks | X10: =COUNTA(ChecklistTable[Task ID]) -> 70
A11: FMS0007 | B11: 46301 | C11: E002 | D11: =IFERROR(_xlfn.XLOOKUP(C11,EmployeeTable[Employee ID],EmployeeTable[Employee Name],"Not found"),IFERROR(INDEX(EmployeeTable[Employee Name],MATCH(C11,EmployeeTable[Employee ID],0)),"Not found")) -> Diya Verma | E11: Site Visit | F11: 46301.771 | G11: 46301.979 | H11: Completed | I11: =IF(G11="","",(G11-F11)*24) -> 5 | J11: =IF(H11="Completed",IF(I11<=4,"Within SLA","Delayed"),"") -> Delayed | L11: TASK0007 | M11: E010 | N11: =IFERROR(_xlfn.XLOOKUP(M11,EmployeeTable[Employee ID],EmployeeTable[Employee Name],"Not found"),IFERROR(INDEX(EmployeeTable[Employee Name],MATCH(M11,EmployeeTable[Employee ID],0)),"Not found")) -> Ira Nair | O11: Opening Checklist | P11: 46311 | Q11: 46315 | S11: Pending | T11: =IF(S11="Completed",IF(R11<=Q11,"On Time","Delayed"),IF(Q11<TODAY(),"Overdue","Pending")) -> Pending | U11: =IF(S11="Completed",IF(R11<=Q11,1,0),0) -> 0
A12: FMS0008 | B12: 46306 | C12: E005 | D12: =IFERROR(_xlfn.XLOOKUP(C12,EmployeeTable[Employee ID],EmployeeTable[Employee Name],"Not found"),IFERROR(INDEX(EmployeeTable[Employee Name],MATCH(C12,EmployeeTable[Employee ID],0)),"Not found")) -> Ishaan Gupta | E12: Stock Audit | F12: 46306.771 | G12: 46307.312 | H12: Completed | I12: =IF(G12="","",(G12-F12)*24) -> 13 | J12: =IF(H12="Completed",IF(I12<=4,"Within SLA","Delayed"),"") -> Delayed | L12: TASK0008 | M12: E007 | N12: =IFERROR(_xlfn.XLOOKUP(M12,EmployeeTable[Employee ID],EmployeeTable[Employee Name],"Not found"),IFERROR(INDEX(EmployeeTable[Employee Name],MATCH(M12,EmployeeTable[Employee ID],0)),"Not found")) -> Rohan Das | O12: Safety Inspection | P12: 46290 | Q12: 46293 | R12: 46292 | S12: Completed | T12: =IF(S12="Completed",IF(R12<=Q12,"On Time","Delayed"),IF(Q12<TODAY(),"Overdue","Pending")) -> On Time | U12: =IF(S12="Completed",IF(R12<=Q12,1,0),0) -> 1
A13: FMS0009 | B13: 46255 | C13: E008 | D13: =IFERROR(_xlfn.XLOOKUP(C13,EmployeeTable[Employee ID],EmployeeTable[Employee Name],"Not found"),IFERROR(INDEX(EmployeeTable[Employee Name],MATCH(C13,EmployeeTable[Employee ID],0)),"Not found")) -> Sana Khan | E13: Customer Follow-up | F13: 46255.375 | G13: 46255.708 | H13: Completed | I13: =IF(G13="","",(G13-F13)*24) -> 8 | J13: =IF(H13="Completed",IF(I13<=4,"Within SLA","Delayed"),"") -> Delayed | L13: TASK0009 | M13: E004 | N13: =IFERROR(_xlfn.XLOOKUP(M13,EmployeeTable[Employee ID],EmployeeTable[Employee Name],"Not found"),IFERROR(INDEX(EmployeeTable[Employee Name],MATCH(M13,EmployeeTable[Employee ID],0)),"Not found")) -> Meera Singh | O13: Stock Reconciliation | P13: 46273 | Q13: 46278 | R13: 46276 | S13: Completed | T13: =IF(S13="Completed",IF(R13<=Q13,"On Time","Delayed"),IF(Q13<TODAY(),"Overdue","Pending")) -> On Time | U13: =IF(S13="Completed",IF(R13<=Q13,1,0),0) -> 1
A14: FMS0010 | B14: 46308 | C14: E001 | D14: =IFERROR(_xlfn.XLOOKUP(C14,EmployeeTable[Employee ID],EmployeeTable[Employee Name],"Not found"),IFERROR(INDEX(EmployeeTable[Employee Name],MATCH(C14,EmployeeTable[Employee ID],0)),"Not found")) -> Aarav Sharma | E14: Delivery Verification | F14: 46308.385 | G14: 46308.469 | H14: Completed | I14: =IF(G14="","",(G14-F14)*24) -> 2 | J14: =IF(H14="Completed",IF(I14<=4,"Within SLA","Delayed"),"") -> Within SLA | L14: TASK0010 | M14: E001 | N14: =IFERROR(_xlfn.XLOOKUP(M14,EmployeeTable[Employee ID],EmployeeTable[Employee Name],"Not found"),IFERROR(INDEX(EmployeeTable[Employee Name],MATCH(M14,EmployeeTable[Employee ID],0)),"Not found")) -> Aarav Sharma | O14: Customer Callback | P14: 46287 | Q14: 46288 | R14: 46290 | S14: Completed | T14: =IF(S14="Completed",IF(R14<=Q14,"On Time","Delayed"),IF(Q14<TODAY(),"Overdue","Pending")) -> Delayed | U14: =IF(S14="Completed",IF(R14<=Q14,1,0),0) -> 0
A15: FMS0011 | B15: 46255 | C15: E004 | D15: =IFERROR(_xlfn.XLOOKUP(C15,EmployeeTable[Employee ID],EmployeeTable[Employee Name],"Not found"),IFERROR(INDEX(EmployeeTable[Employee Name],MATCH(C15,EmployeeTable[Employee ID],0)),"Not found")) -> Meera Singh | E15: Document Collection | F15: 46255.542 | H15: In Progress | I15: =IF(G15="","",(G15-F15)*24) | J15: =IF(H15="Completed",IF(I15<=4,"Within SLA","Delayed"),"") | L15: TASK0011 | M15: E008 | N15: =IFERROR(_xlfn.XLOOKUP(M15,EmployeeTable[Employee ID],EmployeeTable[Employee Name],"Not found"),IFERROR(INDEX(EmployeeTable[Employee Name],MATCH(M15,EmployeeTable[Employee ID],0)),"Not found")) -> Sana Khan | O15: Document Review | P15: 46281 | Q15: 46284 | R15: 46283 | S15: Completed | T15: =IF(S15="Completed",IF(R15<=Q15,"On Time","Delayed"),IF(Q15<TODAY(),"Overdue","Pending")) -> On Time | U15: =IF(S15="Completed",IF(R15<=Q15,1,0),0) -> 1
A16: FMS0012 | B16: 46291 | C16: E007 | D16: =IFERROR(_xlfn.XLOOKUP(C16,EmployeeTable[Employee ID],EmployeeTable[Employee Name],"Not found"),IFERROR(INDEX(EmployeeTable[Employee Name],MATCH(C16,EmployeeTable[Employee ID],0)),"Not found")) -> Rohan Das | E16: Quality Check | F16: 46291.51 | G16: 46291.844 | H16: Completed | I16: =IF(G16="","",(G16-F16)*24) -> 8 | J16: =IF(H16="Completed",IF(I16<=4,"Within SLA","Delayed"),"") -> Delayed | L16: TASK0012 | M16: E005 | N16: =IFERROR(_xlfn.XLOOKUP(M16,EmployeeTable[Employee ID],EmployeeTable[Employee Name],"Not found"),IFERROR(INDEX(EmployeeTable[Employee Name],MATCH(M16,EmployeeTable[Employee ID],0)),"Not found")) -> Ishaan Gupta | O16: End-of-Day Closure | P16: 46307 | Q16: 46310 | R16: 46310 | S16: Completed | T16: =IF(S16="Completed",IF(R16<=Q16,"On Time","Delayed"),IF(Q16<TODAY(),"Overdue","Pending")) -> On Time | U16: =IF(S16="Completed",IF(R16<=Q16,1,0),0) -> 1
A17: FMS0013 | B17: 46269 | C17: E010 | D17: =IFERROR(_xlfn.XLOOKUP(C17,EmployeeTable[Employee ID],EmployeeTable[Employee Name],"Not found"),IFERROR(INDEX(EmployeeTable[Employee Name],MATCH(C17,EmployeeTable[Employee ID],0)),"Not found")) -> Ira Nair | E17: Site Visit | F17: 46269.5 | H17: Pending | I17: =IF(G17="","",(G17-F17)*24) | J17: =IF(H17="Completed",IF(I17<=4,"Within SLA","Delayed"),"") | L17: TASK0013 | M17: E002 | N17: =IFERROR(_xlfn.XLOOKUP(M17,EmployeeTable[Employee ID],EmployeeTable[Employee Name],"Not found"),IFERROR(INDEX(EmployeeTable[Employee Name],MATCH(M17,EmployeeTable[Employee ID],0)),"Not found")) -> Diya Verma | O17: Opening Checklist | P17: 46311 | Q17: 46316 | S17: In Progress | T17: =IF(S17="Completed",IF(R17<=Q17,"On Time","Delayed"),IF(Q17<TODAY(),"Overdue","Pending")) -> Pending | U17: =IF(S17="Completed",IF(R17<=Q17,1,0),0) -> 0
A18: FMS0014 | B18: 46279 | C18: E003 | D18: =IFERROR(_xlfn.XLOOKUP(C18,EmployeeTable[Employee ID],EmployeeTable[Employee Name],"Not found"),IFERROR(INDEX(EmployeeTable[Employee Name],MATCH(C18,EmployeeTable[Employee ID],0)),"Not found")) -> Kabir Patel | E18: Stock Audit | F18: 46279.5 | H18: In Progress | I18: =IF(G18="","",(G18-F18)*24) | J18: =IF(H18="Completed",IF(I18<=4,"Within SLA","Delayed"),"") | L18: TASK0014 | M18: E009 | N18: =IFERROR(_xlfn.XLOOKUP(M18,EmployeeTable[Employee ID],EmployeeTable[Employee Name],"Not found"),IFERROR(INDEX(EmployeeTable[Employee Name],MATCH(M18,EmployeeTable[Employee ID],0)),"Not found")) -> Vivaan Joshi | O18: Safety Inspection | P18: 46312 | Q18: 46317 | S18: In Progress | T18: =IF(S18="Completed",IF(R18<=Q18,"On Time","Delayed"),IF(Q18<TODAY(),"Overdue","Pending")) -> Pending | U18: =IF(S18="Completed",IF(R18<=Q18,1,0),0) -> 0
A19: FMS0015 | B19: 46306 | C19: E006 | D19: =IFERROR(_xlfn.XLOOKUP(C19,EmployeeTable[Employee ID],EmployeeTable[Employee Name],"Not found"),IFERROR(INDEX(EmployeeTable[Employee Name],MATCH(C19,EmployeeTable[Employee ID],0)),"Not found")) -> Ananya Rao | E19: Customer Follow-up | F19: 46306.5 | H19: In Progress | I19: =IF(G19="","",(G19-F19)*24) | J19: =IF(H19="Completed",IF(I19<=4,"Within SLA","Delayed"),"") | L19: TASK0015 | M19: E006 | N19: =IFERROR(_xlfn.XLOOKUP(M19,EmployeeTable[Employee ID],EmployeeTable[Employee Name],"Not found"),IFERROR(INDEX(EmployeeTable[Employee Name],MATCH(M19,EmployeeTable[Employee ID],0)),"Not found")) -> Ananya Rao | O19: Stock Reconciliation | P19: 46312 | Q19: 46315 | S19: Pending | T19: =IF(S19="Completed",IF(R19<=Q19,"On Time","Delayed"),IF(Q19<TODAY(),"Overdue","Pending")) -> Pending | U19: =IF(S19="Completed",IF(R19<=Q19,1,0),0) -> 0
A20: FMS0016 | B20: 46267 | C20: E009 | D20: =IFERROR(_xlfn.XLOOKUP(C20,EmployeeTable[Employee ID],EmployeeTable[Employee Name],"Not found"),IFERROR(INDEX(EmployeeTable[Employee Name],MATCH(C20,EmployeeTable[Employee ID],0)),"Not found")) -> Vivaan Joshi | E20: Delivery Verification | F20: 46267.677 | G20: 46268.01 | H20: Completed | I20: =IF(G20="","",(G20-F20)*24) -> 8 | J20: =IF(H20="Completed",IF(I20<=4,"Within SLA","Delayed"),"") -> Delayed | L20: TASK0016 | M20: E003 | N20: =IFERROR(_xlfn.XLOOKUP(M20,EmployeeTable[Employee ID],EmployeeTable[Employee Name],"Not found"),IFERROR(INDEX(EmployeeTable[Employee Name],MATCH(M20,EmployeeTable[Employee ID],0)),"Not found")) -> Kabir Patel | O20: Customer Callback | P20: 46313 | Q20: 46318 | S20: Pending | T20: =IF(S20="Completed",IF(R20<=Q20,"On Time","Delayed"),IF(Q20<TODAY(),"Overdue","Pending")) -> Pending | U20: =IF(S20="Completed",IF(R20<=Q20,1,0),0) -> 0
A21: FMS0017 | B21: 46301 | C21: E002 | D21: =IFERROR(_xlfn.XLOOKUP(C21,EmployeeTable[Employee ID],EmployeeTable[Employee Name],"Not found"),IFERROR(INDEX(EmployeeTable[Employee Name],MATCH(C21,EmployeeTable[Employee ID],0)),"Not found")) -> Diya Verma | E21: Document Collection | F21: 46301.812 | G21: 46302.229 | H21: Completed | I21: =IF(G21="","",(G21-F21)*24) -> 10 | J21: =IF(H21="Completed",IF(I21<=4,"Within SLA","Delayed"),"") -> Delayed | L21: TASK0017 | M21: E010 | N21: =IFERROR(_xlfn.XLOOKUP(M21,EmployeeTable[Employee ID],EmployeeTable[Employee Name],"Not found"),IFERROR(INDEX(EmployeeTable[Employee Name],MATCH(M21,EmployeeTable[Employee ID],0)),"Not found")) -> Ira Nair | O21: Document Review | P21: 46313 | Q21: 46316 | S21: In Progress | T21: =IF(S21="Completed",IF(R21<=Q21,"On Time","Delayed"),IF(Q21<TODAY(),"Overdue","Pending")) -> Pending | U21: =IF(S21="Completed",IF(R21<=Q21,1,0),0) -> 0
A22: FMS0018 | B22: 46260 | C22: E005 | D22: =IFERROR(_xlfn.XLOOKUP(C22,EmployeeTable[Employee ID],EmployeeTable[Employee Name],"Not found"),IFERROR(INDEX(EmployeeTable[Employee Name],MATCH(C22,EmployeeTable[Employee ID],0)),"Not found")) -> Ishaan Gupta | E22: Quality Check | F22: 46260.531 | G22: 46261.073 | H22: Completed | I22: =IF(G22="","",(G22-F22)*24) -> 13 | J22: =IF(H22="Completed",IF(I22<=4,"Within SLA","Delayed"),"") -> Delayed | L22: TASK0018 | M22: E007 | N22: =IFERROR(_xlfn.XLOOKUP(M22,EmployeeTable[Employee ID],EmployeeTable[Employee Name],"Not found"),IFERROR(INDEX(EmployeeTable[Employee Name],MATCH(M22,EmployeeTable[Employee ID],0)),"Not found")) -> Rohan Das | O22: End-of-Day Closure | P22: 46284 | Q22: 46287 | R22: 46286 | S22: Completed | T22: =IF(S22="Completed",IF(R22<=Q22,"On Time","Delayed"),IF(Q22<TODAY(),"Overdue","Pending")) -> On Time | U22: =IF(S22="Completed",IF(R22<=Q22,1,0),0) -> 1
A23: FMS0019 | B23: 46311 | C23: E008 | D23: =IFERROR(_xlfn.XLOOKUP(C23,EmployeeTable[Employee ID],EmployeeTable[Employee Name],"Not found"),IFERROR(INDEX(EmployeeTable[Employee Name],MATCH(C23,EmployeeTable[Employee ID],0)),"Not found")) -> Sana Khan | E23: Site Visit | F23: 46311.406 | H23: In Progress | I23: =IF(G23="","",(G23-F23)*24) | J23: =IF(H23="Completed",IF(I23<=4,"Within SLA","Delayed"),"") | L23: TASK0019 | M23: E004 | N23: =IFERROR(_xlfn.XLOOKUP(M23,EmployeeTable[Employee ID],EmployeeTable[Employee Name],"Not found"),IFERROR(INDEX(EmployeeTable[Employee Name],MATCH(M23,EmployeeTable[Employee ID],0)),"Not found")) -> Meera Singh | O23: Opening Checklist | P23: 46310 | Q23: 46317 | S23: Pending | T23: =IF(S23="Completed",IF(R23<=Q23,"On Time","Delayed"),IF(Q23<TODAY(),"Overdue","Pending")) -> Pending | U23: =IF(S23="Completed",IF(R23<=Q23,1,0),0) -> 0
A24: FMS0020 | B24: 46312 | C24: E001 | D24: =IFERROR(_xlfn.XLOOKUP(C24,EmployeeTable[Employee ID],EmployeeTable[Employee Name],"Not found"),IFERROR(INDEX(EmployeeTable[Employee Name],MATCH(C24,EmployeeTable[Employee ID],0)),"Not found")) -> Aarav Sharma | E24: Stock Audit | F24: 46312.354 | H24: Pending | I24: =IF(G24="","",(G24-F24)*24) | J24: =IF(H24="Completed",IF(I24<=4,"Within SLA","Delayed"),"") | L24: TASK0020 | M24: E001 | N24: =IFERROR(_xlfn.XLOOKUP(M24,EmployeeTable[Employee ID],EmployeeTable[Employee Name],"Not found"),IFERROR(INDEX(EmployeeTable[Employee Name],MATCH(M24,EmployeeTable[Employee ID],0)),"Not found")) -> Aarav Sharma | O24: Safety Inspection | P24: 46281 | Q24: 46284 | R24: 46284 | S24: Completed | T24: =IF(S24="Completed",IF(R24<=Q24,"On Time","Delayed"),IF(Q24<TODAY(),"Overdue","Pending")) -> On Time | U24: =IF(S24="Completed",IF(R24<=Q24,1,0),0) -> 1
A25: FMS0021 | B25: 46274 | C25: E004 | D25: =IFERROR(_xlfn.XLOOKUP(C25,EmployeeTable[Employee ID],EmployeeTable[Employee Name],"Not found"),IFERROR(INDEX(EmployeeTable[Employee Name],MATCH(C25,EmployeeTable[Employee ID],0)),"Not found")) -> Meera Singh | E25: Customer Follow-up | F25: 46274.51 | H25: Pending | I25: =IF(G25="","",(G25-F25)*24) | J25: =IF(H25="Completed",IF(I25<=4,"Within SLA","Delayed"),"") | L25: TASK0021 | M25: E008 | N25: =IFERROR(_xlfn.XLOOKUP(M25,EmployeeTable[Employee ID],EmployeeTable[Employee Name],"Not found"),IFERROR(INDEX(EmployeeTable[Employee Name],MATCH(M25,EmployeeTable[Employee ID],0)),"Not found")) -> Sana Khan | O25: Stock Reconciliation | P25: 46311 | Q25: 46319 | S25: Pending | T25: =IF(S25="Completed",IF(R25<=Q25,"On Time","Delayed"),IF(Q25<TODAY(),"Overdue","Pending")) -> Pending | U25: =IF(S25="Completed",IF(R25<=Q25,1,0),0) -> 0
A26: FMS0022 | B26: 46279 | C26: E007 | D26: =IFERROR(_xlfn.XLOOKUP(C26,EmployeeTable[Employee ID],EmployeeTable[Employee Name],"Not found"),IFERROR(INDEX(EmployeeTable[Employee Name],MATCH(C26,EmployeeTable[Employee ID],0)),"Not found")) -> Rohan Das | E26: Delivery Verification | F26: 46279.823 | G26: 46279.875 | H26: Completed | I26: =IF(G26="","",(G26-F26)*24) -> 1.25 | J26: =IF(H26="Completed",IF(I26<=4,"Within SLA","Delayed"),"") -> Within SLA | L26: TASK0022 | M26: E005 | N26: =IFERROR(_xlfn.XLOOKUP(M26,EmployeeTable[Employee ID],EmployeeTable[Employee Name],"Not found"),IFERROR(INDEX(EmployeeTable[Employee Name],MATCH(M26,EmployeeTable[Employee ID],0)),"Not found")) -> Ishaan Gupta | O26: Customer Callback | P26: 46299 | Q26: 46301 | R26: 46302 | S26: Completed | T26: =IF(S26="Completed",IF(R26<=Q26,"On Time","Delayed"),IF(Q26<TODAY(),"Overdue","Pending")) -> Delayed | U26: =IF(S26="Completed",IF(R26<=Q26,1,0),0) -> 0
A27: FMS0023 | B27: 46310 | C27: E010 | D27: =IFERROR(_xlfn.XLOOKUP(C27,EmployeeTable[Employee ID],EmployeeTable[Employee Name],"Not found"),IFERROR(INDEX(EmployeeTable[Employee Name],MATCH(C27,EmployeeTable[Employee ID],0)),"Not found")) -> Ira Nair | E27: Document Collection | F27: 46310.927 | G27: 46311.469 | H27: Completed | I27: =IF(G27="","",(G27-F27)*24) -> 13 | J27: =IF(H27="Completed",IF(I27<=4,"Within SLA","Delayed"),"") -> Delayed | L27: TASK0023 | M27: E002 | N27: =IFERROR(_xlfn.XLOOKUP(M27,EmployeeTable[Employee ID],EmployeeTable[Employee Name],"Not found"),IFERROR(INDEX(EmployeeTable[Employee Name],MATCH(M27,EmployeeTable[Employee ID],0)),"Not found")) -> Diya Verma | O27: Document Review | P27: 46309 | Q27: 46310 | R27: 46310 | S27: Completed | T27: =IF(S27="Completed",IF(R27<=Q27,"On Time","Delayed"),IF(Q27<TODAY(),"Overdue","Pending")) -> On Time | U27: =IF(S27="Completed",IF(R27<=Q27,1,0),0) -> 1
A28: FMS0024 | B28: 46291 | C28: E003 | D28: =IFERROR(_xlfn.XLOOKUP(C28,EmployeeTable[Employee ID],EmployeeTable[Employee Name],"Not found"),IFERROR(INDEX(EmployeeTable[Employee Name],MATCH(C28,EmployeeTable[Employee ID],0)),"Not found")) -> Kabir Patel | E28: Quality Check | F28: 46291.719 | G28: 46291.771 | H28: Completed | I28: =IF(G28="","",(G28-F28)*24) -> 1.25 | J28: =IF(H28="Completed",IF(I28<=4,"Within SLA","Delayed"),"") -> Within SLA | L28: TASK0024 | M28: E009 | N28: =IFERROR(_xlfn.XLOOKUP(M28,EmployeeTable[Employee ID],EmployeeTable[Employee Name],"Not found"),IFERROR(INDEX(EmployeeTable[Employee Name],MATCH(M28,EmployeeTable[Employee ID],0)),"Not found")) -> Vivaan Joshi | O28: End-of-Day Closure | P28: 46312 | Q28: 46315 | S28: Pending | T28: =IF(S28="Completed",IF(R28<=Q28,"On Time","Delayed"),IF(Q28<TODAY(),"Overdue","Pending")) -> Pending | U28: =IF(S28="Completed",IF(R28<=Q28,1,0),0) -> 0
A29: FMS0025 | B29: 46295 | C29: E006 | D29: =IFERROR(_xlfn.XLOOKUP(C29,EmployeeTable[Employee ID],EmployeeTable[Employee Name],"Not found"),IFERROR(INDEX(EmployeeTable[Employee Name],MATCH(C29,EmployeeTable[Employee ID],0)),"Not found")) -> Ananya Rao | E29: Site Visit | F29: 46295.542 | H29: In Progress | I29: =IF(G29="","",(G29-F29)*24) | J29: =IF(H29="Completed",IF(I29<=4,"Within SLA","Delayed"),"") | L29: TASK0025 | M29: E006 | N29: =IFERROR(_xlfn.XLOOKUP(M29,EmployeeTable[Employee ID],EmployeeTable[Employee Name],"Not found"),IFERROR(INDEX(EmployeeTable[Employee Name],MATCH(M29,EmployeeTable[Employee ID],0)),"Not found")) -> Ananya Rao | O29: Opening Checklist | P29: 46310 | Q29: 46313 | R29: 46314 | S29: Completed | T29: =IF(S29="Completed",IF(R29<=Q29,"On Time","Delayed"),IF(Q29<TODAY(),"Overdue","Pending")) -> Delayed | U29: =IF(S29="Completed",IF(R29<=Q29,1,0),0) -> 0
A30: FMS0026 | B30: 46301 | C30: E009 | D30: =IFERROR(_xlfn.XLOOKUP(C30,EmployeeTable[Employee ID],EmployeeTable[Employee Name],"Not found"),IFERROR(INDEX(EmployeeTable[Employee Name],MATCH(C30,EmployeeTable[Employee ID],0)),"Not found")) -> Vivaan Joshi | E30: Stock Audit | F30: 46301.76 | H30: Pending | I30: =IF(G30="","",(G30-F30)*24) | J30: =IF(H30="Completed",IF(I30<=4,"Within SLA","Delayed"),"") | L30: TASK0026 | M30: E003 | N30: =IFERROR(_xlfn.XLOOKUP(M30,EmployeeTable[Employee ID],EmployeeTable[Employee Name],"Not found"),IFERROR(INDEX(EmployeeTable[Employee Name],MATCH(M30,EmployeeTable[Employee ID],0)),"Not found")) -> Kabir Patel | O30: Safety Inspection | P30: 46285 | Q30: 46288 | R30: 46288 | S30: Completed | T30: =IF(S30="Completed",IF(R30<=Q30,"On Time","Delayed"),IF(Q30<TODAY(),"Overdue","Pending")) -> On Time | U30: =IF(S30="Completed",IF(R30<=Q30,1,0),0) -> 1
A31: FMS0027 | B31: 46292 | C31: E002 | D31: =IFERROR(_xlfn.XLOOKUP(C31,EmployeeTable[Employee ID],EmployeeTable[Employee Name],"Not found"),IFERROR(INDEX(EmployeeTable[Employee Name],MATCH(C31,EmployeeTable[Employee ID],0)),"Not found")) -> Diya Verma | E31: Customer Follow-up | F31: 46292.865 | H31: Cancelled | I31: =IF(G31="","",(G31-F31)*24) | J31: =IF(H31="Completed",IF(I31<=4,"Within SLA","Delayed"),"") | L31: TASK0027 | M31: E010 | N31: =IFERROR(_xlfn.XLOOKUP(M31,EmployeeTable[Employee ID],EmployeeTable[Employee Name],"Not found"),IFERROR(INDEX(EmployeeTable[Employee Name],MATCH(M31,EmployeeTable[Employee ID],0)),"Not found")) -> Ira Nair | O31: Stock Reconciliation | P31: 46313 | Q31: 46318 | S31: In Progress | T31: =IF(S31="Completed",IF(R31<=Q31,"On Time","Delayed"),IF(Q31<TODAY(),"Overdue","Pending")) -> Pending | U31: =IF(S31="Completed",IF(R31<=Q31,1,0),0) -> 0
A32: FMS0028 | B32: 46267 | C32: E005 | D32: =IFERROR(_xlfn.XLOOKUP(C32,EmployeeTable[Employee ID],EmployeeTable[Employee Name],"Not found"),IFERROR(INDEX(EmployeeTable[Employee Name],MATCH(C32,EmployeeTable[Employee ID],0)),"Not found")) -> Ishaan Gupta | E32: Delivery Verification | F32: 46267.427 | H32: In Progress | I32: =IF(G32="","",(G32-F32)*24) | J32: =IF(H32="Completed",IF(I32<=4,"Within SLA","Delayed"),"") | L32: TASK0028 | M32: E007 | N32: =IFERROR(_xlfn.XLOOKUP(M32,EmployeeTable[Employee ID],EmployeeTable[Employee Name],"Not found"),IFERROR(INDEX(EmployeeTable[Employee Name],MATCH(M32,EmployeeTable[Employee ID],0)),"Not found")) -> Rohan Das | O32: Customer Callback | P32: 46313 | Q32: 46317 | R32: 46315 | S32: Completed | T32: =IF(S32="Completed",IF(R32<=Q32,"On Time","Delayed"),IF(Q32<TODAY(),"Overdue","Pending")) -> On Time | U32: =IF(S32="Completed",IF(R32<=Q32,1,0),0) -> 1
A33: FMS0029 | B33: 46263 | C33: E008 | D33: =IFERROR(_xlfn.XLOOKUP(C33,EmployeeTable[Employee ID],EmployeeTable[Employee Name],"Not found"),IFERROR(INDEX(EmployeeTable[Employee Name],MATCH(C33,EmployeeTable[Employee ID],0)),"Not found")) -> Sana Khan | E33: Document Collection | F33: 46263.844 | H33: In Progress | I33: =IF(G33="","",(G33-F33)*24) | J33: =IF(H33="Completed",IF(I33<=4,"Within SLA","Delayed"),"") | L33: TASK0029 | M33: E004 | N33: =IFERROR(_xlfn.XLOOKUP(M33,EmployeeTable[Employee ID],EmployeeTable[Employee Name],"Not found"),IFERROR(INDEX(EmployeeTable[Employee Name],MATCH(M33,EmployeeTable[Employee ID],0)),"Not found")) -> Meera Singh | O33: Document Review | P33: 46292 | Q33: 46294 | S33: Pending | T33: =IF(S33="Completed",IF(R33<=Q33,"On Time","Delayed"),IF(Q33<TODAY(),"Overdue","Pending")) -> Overdue | U33: =IF(S33="Completed",IF(R33<=Q33,1,0),0) -> 0
A34: FMS0030 | B34: 46313 | C34: E001 | D34: =IFERROR(_xlfn.XLOOKUP(C34,EmployeeTable[Employee ID],EmployeeTable[Employee Name],"Not found"),IFERROR(INDEX(EmployeeTable[Employee Name],MATCH(C34,EmployeeTable[Employee ID],0)),"Not found")) -> Aarav Sharma | E34: Quality Check | F34: 46313.438 | H34: Pending | I34: =IF(G34="","",(G34-F34)*24) | J34: =IF(H34="Completed",IF(I34<=4,"Within SLA","Delayed"),"") | L34: TASK0030 | M34: E001 | N34: =IFERROR(_xlfn.XLOOKUP(M34,EmployeeTable[Employee ID],EmployeeTable[Employee Name],"Not found"),IFERROR(INDEX(EmployeeTable[Employee Name],MATCH(M34,EmployeeTable[Employee ID],0)),"Not found")) -> Aarav Sharma | O34: End-of-Day Closure | P34: 46288 | Q34: 46292 | S34: Pending | T34: =IF(S34="Completed",IF(R34<=Q34,"On Time","Delayed"),IF(Q34<TODAY(),"Overdue","Pending")) -> Overdue | U34: =IF(S34="Completed",IF(R34<=Q34,1,0),0) -> 0
A35: FMS0031 | B35: 46288 | C35: E004 | D35: =IFERROR(_xlfn.XLOOKUP(C35,EmployeeTable[Employee ID],EmployeeTable[Employee Name],"Not found"),IFERROR(INDEX(EmployeeTable[Employee Name],MATCH(C35,EmployeeTable[Employee ID],0)),"Not found")) -> Meera Singh | E35: Site Visit | F35: 46288.844 | G35: 46289.385 | H35: Completed | I35: =IF(G35="","",(G35-F35)*24) -> 13 | J35: =IF(H35="Completed",IF(I35<=4,"Within SLA","Delayed"),"") -> Delayed | L35: TASK0031 | M35: E008 | N35: =IFERROR(_xlfn.XLOOKUP(M35,EmployeeTable[Employee ID],EmployeeTable[Employee Name],"Not found"),IFERROR(INDEX(EmployeeTable[Employee Name],MATCH(M35,EmployeeTable[Employee ID],0)),"Not found")) -> Sana Khan | O35: Opening Checklist | P35: 46280 | Q35: 46284 | S35: In Progress | T35: =IF(S35="Completed",IF(R35<=Q35,"On Time","Delayed"),IF(Q35<TODAY(),"Overdue","Pending")) -> Overdue | U35: =IF(S35="Completed",IF(R35<=Q35,1,0),0) -> 0
A36: FMS0032 | B36: 46270 | C36: E007 | D36: =IFERROR(_xlfn.XLOOKUP(C36,EmployeeTable[Employee ID],EmployeeTable[Employee Name],"Not found"),IFERROR(INDEX(EmployeeTable[Employee Name],MATCH(C36,EmployeeTable[Employee ID],0)),"Not found")) -> Rohan Das | E36: Stock Audit | F36: 46270.406 | H36: In Progress | I36: =IF(G36="","",(G36-F36)*24) | J36: =IF(H36="Completed",IF(I36<=4,"Within SLA","Delayed"),"") | L36: TASK0032 | M36: E005 | N36: =IFERROR(_xlfn.XLOOKUP(M36,EmployeeTable[Employee ID],EmployeeTable[Employee Name],"Not found"),IFERROR(INDEX(EmployeeTable[Employee Name],MATCH(M36,EmployeeTable[Employee ID],0)),"Not found")) -> Ishaan Gupta | O36: Safety Inspection | P36: 46283 | Q36: 46284 | R36: 46284 | S36: Completed | T36: =IF(S36="Completed",IF(R36<=Q36,"On Time","Delayed"),IF(Q36<TODAY(),"Overdue","Pending")) -> On Time | U36: =IF(S36="Completed",IF(R36<=Q36,1,0),0) -> 1
A37: FMS0033 | B37: 46260 | C37: E010 | D37: =IFERROR(_xlfn.XLOOKUP(C37,EmployeeTable[Employee ID],EmployeeTable[Employee Name],"Not found"),IFERROR(INDEX(EmployeeTable[Employee Name],MATCH(C37,EmployeeTable[Employee ID],0)),"Not found")) -> Ira Nair | E37: Customer Follow-up | F37: 46260.635 | G37: 46260.844 | H37: Completed | I37: =IF(G37="","",(G37-F37)*24) -> 5 | J37: =IF(H37="Completed",IF(I37<=4,"Within SLA","Delayed"),"") -> Delayed | L37: TASK0033 | M37: E002 | N37: =IFERROR(_xlfn.XLOOKUP(M37,EmployeeTable[Employee ID],EmployeeTable[Employee Name],"Not found"),IFERROR(INDEX(EmployeeTable[Employee Name],MATCH(M37,EmployeeTable[Employee ID],0)),"Not found")) -> Diya Verma | O37: Stock Reconciliation | P37: 46313 | Q37: 46316 | R37: 46318 | S37: Completed | T37: =IF(S37="Completed",IF(R37<=Q37,"On Time","Delayed"),IF(Q37<TODAY(),"Overdue","Pending")) -> Delayed | U37: =IF(S37="Completed",IF(R37<=Q37,1,0),0) -> 0
A38: FMS0034 | B38: 46292 | C38: E003 | D38: =IFERROR(_xlfn.XLOOKUP(C38,EmployeeTable[Employee ID],EmployeeTable[Employee Name],"Not found"),IFERROR(INDEX(EmployeeTable[Employee Name],MATCH(C38,EmployeeTable[Employee ID],0)),"Not found")) -> Kabir Patel | E38: Delivery Verification | F38: 46292.51 | G38: 46292.927 | H38: Completed | I38: =IF(G38="","",(G38-F38)*24) -> 10 | J38: =IF(H38="Completed",IF(I38<=4,"Within SLA","Delayed"),"") -> Delayed | L38: TASK0034 | M38: E009 | N38: =IFERROR(_xlfn.XLOOKUP(M38,EmployeeTable[Employee ID],EmployeeTable[Employee Name],"Not found"),IFERROR(INDEX(EmployeeTable[Employee Name],MATCH(M38,EmployeeTable[Employee ID],0)),"Not found")) -> Vivaan Joshi | O38: Customer Callback | P38: 46289 | Q38: 46294 | R38: 46294 | S38: Completed | T38: =IF(S38="Completed",IF(R38<=Q38,"On Time","Delayed"),IF(Q38<TODAY(),"Overdue","Pending")) -> On Time | U38: =IF(S38="Completed",IF(R38<=Q38,1,0),0) -> 1
A39: FMS0035 | B39: 46302 | C39: E006 | D39: =IFERROR(_xlfn.XLOOKUP(C39,EmployeeTable[Employee ID],EmployeeTable[Employee Name],"Not found"),IFERROR(INDEX(EmployeeTable[Employee Name],MATCH(C39,EmployeeTable[Employee ID],0)),"Not found")) -> Ananya Rao | E39: Document Collection | F39: 46302.604 | G39: 46302.656 | H39: Completed | I39: =IF(G39="","",(G39-F39)*24) -> 1.25 | J39: =IF(H39="Completed",IF(I39<=4,"Within SLA","Delayed"),"") -> Within SLA | L39: TASK0035 | M39: E006 | N39: =IFERROR(_xlfn.XLOOKUP(M39,EmployeeTable[Employee ID],EmployeeTable[Employee Name],"Not found"),IFERROR(INDEX(EmployeeTable[Employee Name],MATCH(M39,EmployeeTable[Employee ID],0)),"Not found")) -> Ananya Rao | O39: Document Review | P39: 46306 | Q39: 46310 | R39: 46310 | S39: Completed | T39: =IF(S39="Completed",IF(R39<=Q39,"On Time","Delayed"),IF(Q39<TODAY(),"Overdue","Pending")) -> On Time | U39: =IF(S39="Completed",IF(R39<=Q39,1,0),0) -> 1
A40: FMS0036 | B40: 46265 | C40: E009 | D40: =IFERROR(_xlfn.XLOOKUP(C40,EmployeeTable[Employee ID],EmployeeTable[Employee Name],"Not found"),IFERROR(INDEX(EmployeeTable[Employee Name],MATCH(C40,EmployeeTable[Employee ID],0)),"Not found")) -> Vivaan Joshi | E40: Quality Check | F40: 46265.521 | H40: Pending | I40: =IF(G40="","",(G40-F40)*24) | J40: =IF(H40="Completed",IF(I40<=4,"Within SLA","Delayed"),"") | L40: TASK0036 | M40: E003 | N40: =IFERROR(_xlfn.XLOOKUP(M40,EmployeeTable[Employee ID],EmployeeTable[Employee Name],"Not found"),IFERROR(INDEX(EmployeeTable[Employee Name],MATCH(M40,EmployeeTable[Employee ID],0)),"Not found")) -> Kabir Patel | O40: End-of-Day Closure | P40: 46277 | Q40: 46281 | S40: Pending | T40: =IF(S40="Completed",IF(R40<=Q40,"On Time","Delayed"),IF(Q40<TODAY(),"Overdue","Pending")) -> Overdue | U40: =IF(S40="Completed",IF(R40<=Q40,1,0),0) -> 0
A41: FMS0037 | B41: 46289 | C41: E002 | D41: =IFERROR(_xlfn.XLOOKUP(C41,EmployeeTable[Employee ID],EmployeeTable[Employee Name],"Not found"),IFERROR(INDEX(EmployeeTable[Employee Name],MATCH(C41,EmployeeTable[Employee ID],0)),"Not found")) -> Diya Verma | E41: Site Visit | F41: 46289.771 | H41: In Progress | I41: =IF(G41="","",(G41-F41)*24) | J41: =IF(H41="Completed",IF(I41<=4,"Within SLA","Delayed"),"") | L41: TASK0037 | M41: E010 | N41: =IFERROR(_xlfn.XLOOKUP(M41,EmployeeTable[Employee ID],EmployeeTable[Employee Name],"Not found"),IFERROR(INDEX(EmployeeTable[Employee Name],MATCH(M41,EmployeeTable[Employee ID],0)),"Not found")) -> Ira Nair | O41: Opening Checklist | P41: 46309 | Q41: 46314 | R41: 46314 | S41: Completed | T41: =IF(S41="Completed",IF(R41<=Q41,"On Time","Delayed"),IF(Q41<TODAY(),"Overdue","Pending")) -> On Time | U41: =IF(S41="Completed",IF(R41<=Q41,1,0),0) -> 1
A42: FMS0038 | B42: 46307 | C42: E005 | D42: =IFERROR(_xlfn.XLOOKUP(C42,EmployeeTable[Employee ID],EmployeeTable[Employee Name],"Not found"),IFERROR(INDEX(EmployeeTable[Employee Name],MATCH(C42,EmployeeTable[Employee ID],0)),"Not found")) -> Ishaan Gupta | E42: Stock Audit | F42: 46307.938 | G42: 46308.083 | H42: Completed | I42: =IF(G42="","",(G42-F42)*24) -> 3.5 | J42: =IF(H42="Completed",IF(I42<=4,"Within SLA","Delayed"),"") -> Within SLA | L42: TASK0038 | M42: E007 | N42: =IFERROR(_xlfn.XLOOKUP(M42,EmployeeTable[Employee ID],EmployeeTable[Employee Name],"Not found"),IFERROR(INDEX(EmployeeTable[Employee Name],MATCH(M42,EmployeeTable[Employee ID],0)),"Not found")) -> Rohan Das | O42: Safety Inspection | P42: 46303 | Q42: 46303 | R42: 46303 | S42: Completed | T42: =IF(S42="Completed",IF(R42<=Q42,"On Time","Delayed"),IF(Q42<TODAY(),"Overdue","Pending")) -> On Time | U42: =IF(S42="Completed",IF(R42<=Q42,1,0),0) -> 1
A43: FMS0039 | B43: 46312 | C43: E008 | D43: =IFERROR(_xlfn.XLOOKUP(C43,EmployeeTable[Employee ID],EmployeeTable[Employee Name],"Not found"),IFERROR(INDEX(EmployeeTable[Employee Name],MATCH(C43,EmployeeTable[Employee ID],0)),"Not found")) -> Sana Khan | E43: Customer Follow-up | F43: 46312.406 | G43: 46312.948 | H43: Completed | I43: =IF(G43="","",(G43-F43)*24) -> 13 | J43: =IF(H43="Completed",IF(I43<=4,"Within SLA","Delayed"),"") -> Delayed | L43: TASK0039 | M43: E004 | N43: =IFERROR(_xlfn.XLOOKUP(M43,EmployeeTable[Employee ID],EmployeeTable[Employee Name],"Not found"),IFERROR(INDEX(EmployeeTable[Employee Name],MATCH(M43,EmployeeTable[Employee ID],0)),"Not found")) -> Meera Singh | O43: Stock Reconciliation | P43: 46301 | Q43: 46304 | R43: 46304 | S43: Completed | T43: =IF(S43="Completed",IF(R43<=Q43,"On Time","Delayed"),IF(Q43<TODAY(),"Overdue","Pending")) -> On Time | U43: =IF(S43="Completed",IF(R43<=Q43,1,0),0) -> 1
A44: FMS0040 | B44: 46294 | C44: E001 | D44: =IFERROR(_xlfn.XLOOKUP(C44,EmployeeTable[Employee ID],EmployeeTable[Employee Name],"Not found"),IFERROR(INDEX(EmployeeTable[Employee Name],MATCH(C44,EmployeeTable[Employee ID],0)),"Not found")) -> Aarav Sharma | E44: Delivery Verification | F44: 46294.583 | G44: 46294.917 | H44: Completed | I44: =IF(G44="","",(G44-F44)*24) -> 8 | J44: =IF(H44="Completed",IF(I44<=4,"Within SLA","Delayed"),"") -> Delayed | L44: TASK0040 | M44: E001 | N44: =IFERROR(_xlfn.XLOOKUP(M44,EmployeeTable[Employee ID],EmployeeTable[Employee Name],"Not found"),IFERROR(INDEX(EmployeeTable[Employee Name],MATCH(M44,EmployeeTable[Employee ID],0)),"Not found")) -> Aarav Sharma | O44: Customer Callback | P44: 46297 | Q44: 46300 | R44: 46298 | S44: Completed | T44: =IF(S44="Completed",IF(R44<=Q44,"On Time","Delayed"),IF(Q44<TODAY(),"Overdue","Pending")) -> On Time | U44: =IF(S44="Completed",IF(R44<=Q44,1,0),0) -> 1
A45: FMS0041 | B45: 46302 | C45: E004 | D45: =IFERROR(_xlfn.XLOOKUP(C45,EmployeeTable[Employee ID],EmployeeTable[Employee Name],"Not found"),IFERROR(INDEX(EmployeeTable[Employee Name],MATCH(C45,EmployeeTable[Employee ID],0)),"Not found")) -> Meera Singh | E45: Document Collection | F45: 46302.5 | H45: Pending | I45: =IF(G45="","",(G45-F45)*24) | J45: =IF(H45="Completed",IF(I45<=4,"Within SLA","Delayed"),"") | L45: TASK0041 | M45: E008 | N45: =IFERROR(_xlfn.XLOOKUP(M45,EmployeeTable[Employee ID],EmployeeTable[Employee Name],"Not found"),IFERROR(INDEX(EmployeeTable[Employee Name],MATCH(M45,EmployeeTable[Employee ID],0)),"Not found")) -> Sana Khan | O45: Document Review | P45: 46284 | Q45: 46284 | S45: Pending | T45: =IF(S45="Completed",IF(R45<=Q45,"On Time","Delayed"),IF(Q45<TODAY(),"Overdue","Pending")) -> Overdue | U45: =IF(S45="Completed",IF(R45<=Q45,1,0),0) -> 0
A46: FMS0042 | B46: 46314 | C46: E007 | D46: =IFERROR(_xlfn.XLOOKUP(C46,EmployeeTable[Employee ID],EmployeeTable[Employee Name],"Not found"),IFERROR(INDEX(EmployeeTable[Employee Name],MATCH(C46,EmployeeTable[Employee ID],0)),"Not found")) -> Rohan Das | E46: Quality Check | F46: 46314.677 | G46: 46314.729 | H46: Completed | I46: =IF(G46="","",(G46-F46)*24) -> 1.25 | J46: =IF(H46="Completed",IF(I46<=4,"Within SLA","Delayed"),"") -> Within SLA | L46: TASK0042 | M46: E005 | N46: =IFERROR(_xlfn.XLOOKUP(M46,EmployeeTable[Employee ID],EmployeeTable[Employee Name],"Not found"),IFERROR(INDEX(EmployeeTable[Employee Name],MATCH(M46,EmployeeTable[Employee ID],0)),"Not found")) -> Ishaan Gupta | O46: End-of-Day Closure | P46: 46311 | Q46: 46313 | R46: 46311 | S46: Completed | T46: =IF(S46="Completed",IF(R46<=Q46,"On Time","Delayed"),IF(Q46<TODAY(),"Overdue","Pending")) -> On Time | U46: =IF(S46="Completed",IF(R46<=Q46,1,0),0) -> 1
A47: FMS0043 | B47: 46272 | C47: E010 | D47: =IFERROR(_xlfn.XLOOKUP(C47,EmployeeTable[Employee ID],EmployeeTable[Employee Name],"Not found"),IFERROR(INDEX(EmployeeTable[Employee Name],MATCH(C47,EmployeeTable[Employee ID],0)),"Not found")) -> Ira Nair | E47: Site Visit | F47: 46272.938 | H47: Pending | I47: =IF(G47="","",(G47-F47)*24) | J47: =IF(H47="Completed",IF(I47<=4,"Within SLA","Delayed"),"") | L47: TASK0043 | M47: E002 | N47: =IFERROR(_xlfn.XLOOKUP(M47,EmployeeTable[Employee ID],EmployeeTable[Employee Name],"Not found"),IFERROR(INDEX(EmployeeTable[Employee Name],MATCH(M47,EmployeeTable[Employee ID],0)),"Not found")) -> Diya Verma | O47: Opening Checklist | P47: 46273 | Q47: 46273 | S47: Pending | T47: =IF(S47="Completed",IF(R47<=Q47,"On Time","Delayed"),IF(Q47<TODAY(),"Overdue","Pending")) -> Overdue | U47: =IF(S47="Completed",IF(R47<=Q47,1,0),0) -> 0
A48: FMS0044 | B48: 46272 | C48: E003 | D48: =IFERROR(_xlfn.XLOOKUP(C48,EmployeeTable[Employee ID],EmployeeTable[Employee Name],"Not found"),IFERROR(INDEX(EmployeeTable[Employee Name],MATCH(C48,EmployeeTable[Employee ID],0)),"Not found")) -> Kabir Patel | E48: Stock Audit | F48: 46272.875 | H48: Pending | I48: =IF(G48="","",(G48-F48)*24) | J48: =IF(H48="Completed",IF(I48<=4,"Within SLA","Delayed"),"") | L48: TASK0044 | M48: E009 | N48: =IFERROR(_xlfn.XLOOKUP(M48,EmployeeTable[Employee ID],EmployeeTable[Employee Name],"Not found"),IFERROR(INDEX(EmployeeTable[Employee Name],MATCH(M48,EmployeeTable[Employee ID],0)),"Not found")) -> Vivaan Joshi | O48: Safety Inspection | P48: 46299 | Q48: 46300 | S48: Pending | T48: =IF(S48="Completed",IF(R48<=Q48,"On Time","Delayed"),IF(Q48<TODAY(),"Overdue","Pending")) -> Overdue | U48: =IF(S48="Completed",IF(R48<=Q48,1,0),0) -> 0
A49: FMS0045 | B49: 46295 | C49: E006 | D49: =IFERROR(_xlfn.XLOOKUP(C49,EmployeeTable[Employee ID],EmployeeTable[Employee Name],"Not found"),IFERROR(INDEX(EmployeeTable[Employee Name],MATCH(C49,EmployeeTable[Employee ID],0)),"Not found")) -> Ananya Rao | E49: Customer Follow-up | F49: 46295.688 | H49: Pending | I49: =IF(G49="","",(G49-F49)*24) | J49: =IF(H49="Completed",IF(I49<=4,"Within SLA","Delayed"),"") | L49: TASK0045 | M49: E006 | N49: =IFERROR(_xlfn.XLOOKUP(M49,EmployeeTable[Employee ID],EmployeeTable[Employee Name],"Not found"),IFERROR(INDEX(EmployeeTable[Employee Name],MATCH(M49,EmployeeTable[Employee ID],0)),"Not found")) -> Ananya Rao | O49: Stock Reconciliation | P49: 46275 | Q49: 46276 | R49: 46276 | S49: Completed | T49: =IF(S49="Completed",IF(R49<=Q49,"On Time","Delayed"),IF(Q49<TODAY(),"Overdue","Pending")) -> On Time | U49: =IF(S49="Completed",IF(R49<=Q49,1,0),0) -> 1
A50: FMS0046 | B50: 46294 | C50: E009 | D50: =IFERROR(_xlfn.XLOOKUP(C50,EmployeeTable[Employee ID],EmployeeTable[Employee Name],"Not found"),IFERROR(INDEX(EmployeeTable[Employee Name],MATCH(C50,EmployeeTable[Employee ID],0)),"Not found")) -> Vivaan Joshi | E50: Delivery Verification | F50: 46294.604 | G50: 46294.688 | H50: Completed | I50: =IF(G50="","",(G50-F50)*24) -> 2 | J50: =IF(H50="Completed",IF(I50<=4,"Within SLA","Delayed"),"") -> Within SLA | L50: TASK0046 | M50: E003 | N50: =IFERROR(_xlfn.XLOOKUP(M50,EmployeeTable[Employee ID],EmployeeTable[Employee Name],"Not found"),IFERROR(INDEX(EmployeeTable[Employee Name],MATCH(M50,EmployeeTable[Employee ID],0)),"Not found")) -> Kabir Patel | O50: Customer Callback | P50: 46272 | Q50: 46272 | R50: 46271 | S50: Completed | T50: =IF(S50="Completed",IF(R50<=Q50,"On Time","Delayed"),IF(Q50<TODAY(),"Overdue","Pending")) -> On Time | U50: =IF(S50="Completed",IF(R50<=Q50,1,0),0) -> 1
A51: FMS0047 | B51: 46288 | C51: E002 | D51: =IFERROR(_xlfn.XLOOKUP(C51,EmployeeTable[Employee ID],EmployeeTable[Employee Name],"Not found"),IFERROR(INDEX(EmployeeTable[Employee Name],MATCH(C51,EmployeeTable[Employee ID],0)),"Not found")) -> Diya Verma | E51: Document Collection | F51: 46288.781 | H51: Pending | I51: =IF(G51="","",(G51-F51)*24) | J51: =IF(H51="Completed",IF(I51<=4,"Within SLA","Delayed"),"") | L51: TASK0047 | M51: E010 | N51: =IFERROR(_xlfn.XLOOKUP(M51,EmployeeTable[Employee ID],EmployeeTable[Employee Name],"Not found"),IFERROR(INDEX(EmployeeTable[Employee Name],MATCH(M51,EmployeeTable[Employee ID],0)),"Not found")) -> Ira Nair | O51: Document Review | P51: 46285 | Q51: 46290 | R51: 46290 | S51: Completed | T51: =IF(S51="Completed",IF(R51<=Q51,"On Time","Delayed"),IF(Q51<TODAY(),"Overdue","Pending")) -> On Time | U51: =IF(S51="Completed",IF(R51<=Q51,1,0),0) -> 1
A52: FMS0048 | B52: 46257 | C52: E005 | D52: =IFERROR(_xlfn.XLOOKUP(C52,EmployeeTable[Employee ID],EmployeeTable[Employee Name],"Not found"),IFERROR(INDEX(EmployeeTable[Employee Name],MATCH(C52,EmployeeTable[Employee ID],0)),"Not found")) -> Ishaan Gupta | E52: Quality Check | F52: 46257.438 | G52: 46257.979 | H52: Completed | I52: =IF(G52="","",(G52-F52)*24) -> 13 | J52: =IF(H52="Completed",IF(I52<=4,"Within SLA","Delayed"),"") -> Delayed | L52: TASK0048 | M52: E007 | N52: =IFERROR(_xlfn.XLOOKUP(M52,EmployeeTable[Employee ID],EmployeeTable[Employee Name],"Not found"),IFERROR(INDEX(EmployeeTable[Employee Name],MATCH(M52,EmployeeTable[Employee ID],0)),"Not found")) -> Rohan Das | O52: End-of-Day Closure | P52: 46304 | Q52: 46308 | R52: 46310 | S52: Completed | T52: =IF(S52="Completed",IF(R52<=Q52,"On Time","Delayed"),IF(Q52<TODAY(),"Overdue","Pending")) -> Delayed | U52: =IF(S52="Completed",IF(R52<=Q52,1,0),0) -> 0
A53: FMS0049 | B53: 46314 | C53: E008 | D53: =IFERROR(_xlfn.XLOOKUP(C53,EmployeeTable[Employee ID],EmployeeTable[Employee Name],"Not found"),IFERROR(INDEX(EmployeeTable[Employee Name],MATCH(C53,EmployeeTable[Employee ID],0)),"Not found")) -> Sana Khan | E53: Site Visit | F53: 46314.521 | G53: 46315.062 | H53: Completed | I53: =IF(G53="","",(G53-F53)*24) -> 13 | J53: =IF(H53="Completed",IF(I53<=4,"Within SLA","Delayed"),"") -> Delayed | L53: TASK0049 | M53: E004 | N53: =IFERROR(_xlfn.XLOOKUP(M53,EmployeeTable[Employee ID],EmployeeTable[Employee Name],"Not found"),IFERROR(INDEX(EmployeeTable[Employee Name],MATCH(M53,EmployeeTable[Employee ID],0)),"Not found")) -> Meera Singh | O53: Opening Checklist | P53: 46307 | Q53: 46308 | S53: In Progress | T53: =IF(S53="Completed",IF(R53<=Q53,"On Time","Delayed"),IF(Q53<TODAY(),"Overdue","Pending")) -> Overdue | U53: =IF(S53="Completed",IF(R53<=Q53,1,0),0) -> 0
A54: FMS0050 | B54: 46277 | C54: E001 | D54: =IFERROR(_xlfn.XLOOKUP(C54,EmployeeTable[Employee ID],EmployeeTable[Employee Name],"Not found"),IFERROR(INDEX(EmployeeTable[Employee Name],MATCH(C54,EmployeeTable[Employee ID],0)),"Not found")) -> Aarav Sharma | E54: Stock Audit | F54: 46277.729 | G54: 46277.938 | H54: Completed | I54: =IF(G54="","",(G54-F54)*24) -> 5 | J54: =IF(H54="Completed",IF(I54<=4,"Within SLA","Delayed"),"") -> Delayed | L54: TASK0050 | M54: E001 | N54: =IFERROR(_xlfn.XLOOKUP(M54,EmployeeTable[Employee ID],EmployeeTable[Employee Name],"Not found"),IFERROR(INDEX(EmployeeTable[Employee Name],MATCH(M54,EmployeeTable[Employee ID],0)),"Not found")) -> Aarav Sharma | O54: Safety Inspection | P54: 46308 | Q54: 46312 | R54: 46312 | S54: Completed | T54: =IF(S54="Completed",IF(R54<=Q54,"On Time","Delayed"),IF(Q54<TODAY(),"Overdue","Pending")) -> On Time | U54: =IF(S54="Completed",IF(R54<=Q54,1,0),0) -> 1
L55: TASK0051 | M55: E008 | N55: =IFERROR(_xlfn.XLOOKUP(M55,EmployeeTable[Employee ID],EmployeeTable[Employee Name],"Not found"),IFERROR(INDEX(EmployeeTable[Employee Name],MATCH(M55,EmployeeTable[Employee ID],0)),"Not found")) -> Sana Khan | O55: Stock Reconciliation | P55: 46278 | Q55: 46283 | S55: In Progress | T55: =IF(S55="Completed",IF(R55<=Q55,"On Time","Delayed"),IF(Q55<TODAY(),"Overdue","Pending")) -> Overdue | U55: =IF(S55="Completed",IF(R55<=Q55,1,0),0) -> 0
L56: TASK0052 | M56: E005 | N56: =IFERROR(_xlfn.XLOOKUP(M56,EmployeeTable[Employee ID],EmployeeTable[Employee Name],"Not found"),IFERROR(INDEX(EmployeeTable[Employee Name],MATCH(M56,EmployeeTable[Employee ID],0)),"Not found")) -> Ishaan Gupta | O56: Customer Callback | P56: 46290 | Q56: 46293 | S56: In Progress | T56: =IF(S56="Completed",IF(R56<=Q56,"On Time","Delayed"),IF(Q56<TODAY(),"Overdue","Pending")) -> Overdue | U56: =IF(S56="Completed",IF(R56<=Q56,1,0),0) -> 0
L57: TASK0053 | M57: E002 | N57: =IFERROR(_xlfn.XLOOKUP(M57,EmployeeTable[Employee ID],EmployeeTable[Employee Name],"Not found"),IFERROR(INDEX(EmployeeTable[Employee Name],MATCH(M57,EmployeeTable[Employee ID],0)),"Not found")) -> Diya Verma | O57: Document Review | P57: 46302 | Q57: 46302 | R57: 46304 | S57: Completed | T57: =IF(S57="Completed",IF(R57<=Q57,"On Time","Delayed"),IF(Q57<TODAY(),"Overdue","Pending")) -> Delayed | U57: =IF(S57="Completed",IF(R57<=Q57,1,0),0) -> 0
L58: TASK0054 | M58: E009 | N58: =IFERROR(_xlfn.XLOOKUP(M58,EmployeeTable[Employee ID],EmployeeTable[Employee Name],"Not found"),IFERROR(INDEX(EmployeeTable[Employee Name],MATCH(M58,EmployeeTable[Employee ID],0)),"Not found")) -> Vivaan Joshi | O58: End-of-Day Closure | P58: 46299 | Q58: 46299 | S58: Pending | T58: =IF(S58="Completed",IF(R58<=Q58,"On Time","Delayed"),IF(Q58<TODAY(),"Overdue","Pending")) -> Overdue | U58: =IF(S58="Completed",IF(R58<=Q58,1,0),0) -> 0
L59: TASK0055 | M59: E006 | N59: =IFERROR(_xlfn.XLOOKUP(M59,EmployeeTable[Employee ID],EmployeeTable[Employee Name],"Not found"),IFERROR(INDEX(EmployeeTable[Employee Name],MATCH(M59,EmployeeTable[Employee ID],0)),"Not found")) -> Ananya Rao | O59: Opening Checklist | P59: 46295 | Q59: 46300 | R59: 46298 | S59: Completed | T59: =IF(S59="Completed",IF(R59<=Q59,"On Time","Delayed"),IF(Q59<TODAY(),"Overdue","Pending")) -> On Time | U59: =IF(S59="Completed",IF(R59<=Q59,1,0),0) -> 1
L60: TASK0056 | M60: E003 | N60: =IFERROR(_xlfn.XLOOKUP(M60,EmployeeTable[Employee ID],EmployeeTable[Employee Name],"Not found"),IFERROR(INDEX(EmployeeTable[Employee Name],MATCH(M60,EmployeeTable[Employee ID],0)),"Not found")) -> Kabir Patel | O60: Safety Inspection | P60: 46278 | Q60: 46278 | R60: 46278 | S60: Completed | T60: =IF(S60="Completed",IF(R60<=Q60,"On Time","Delayed"),IF(Q60<TODAY(),"Overdue","Pending")) -> On Time | U60: =IF(S60="Completed",IF(R60<=Q60,1,0),0) -> 1
L61: TASK0057 | M61: E010 | N61: =IFERROR(_xlfn.XLOOKUP(M61,EmployeeTable[Employee ID],EmployeeTable[Employee Name],"Not found"),IFERROR(INDEX(EmployeeTable[Employee Name],MATCH(M61,EmployeeTable[Employee ID],0)),"Not found")) -> Ira Nair | O61: Stock Reconciliation | P61: 46272 | Q61: 46274 | R61: 46276 | S61: Completed | T61: =IF(S61="Completed",IF(R61<=Q61,"On Time","Delayed"),IF(Q61<TODAY(),"Overdue","Pending")) -> Delayed | U61: =IF(S61="Completed",IF(R61<=Q61,1,0),0) -> 0
L62: TASK0058 | M62: E007 | N62: =IFERROR(_xlfn.XLOOKUP(M62,EmployeeTable[Employee ID],EmployeeTable[Employee Name],"Not found"),IFERROR(INDEX(EmployeeTable[Employee Name],MATCH(M62,EmployeeTable[Employee ID],0)),"Not found")) -> Rohan Das | O62: Customer Callback | P62: 46293 | Q62: 46293 | S62: Pending | T62: =IF(S62="Completed",IF(R62<=Q62,"On Time","Delayed"),IF(Q62<TODAY(),"Overdue","Pending")) -> Overdue | U62: =IF(S62="Completed",IF(R62<=Q62,1,0),0) -> 0
L63: TASK0059 | M63: E004 | N63: =IFERROR(_xlfn.XLOOKUP(M63,EmployeeTable[Employee ID],EmployeeTable[Employee Name],"Not found"),IFERROR(INDEX(EmployeeTable[Employee Name],MATCH(M63,EmployeeTable[Employee ID],0)),"Not found")) -> Meera Singh | O63: Document Review | P63: 46283 | Q63: 46283 | R63: 46283 | S63: Completed | T63: =IF(S63="Completed",IF(R63<=Q63,"On Time","Delayed"),IF(Q63<TODAY(),"Overdue","Pending")) -> On Time | U63: =IF(S63="Completed",IF(R63<=Q63,1,0),0) -> 1
L64: TASK0060 | M64: E001 | N64: =IFERROR(_xlfn.XLOOKUP(M64,EmployeeTable[Employee ID],EmployeeTable[Employee Name],"Not found"),IFERROR(INDEX(EmployeeTable[Employee Name],MATCH(M64,EmployeeTable[Employee ID],0)),"Not found")) -> Aarav Sharma | O64: End-of-Day Closure | P64: 46274 | Q64: 46277 | S64: Pending | T64: =IF(S64="Completed",IF(R64<=Q64,"On Time","Delayed"),IF(Q64<TODAY(),"Overdue","Pending")) -> Overdue | U64: =IF(S64="Completed",IF(R64<=Q64,1,0),0) -> 0
L65: TASK0061 | M65: E008 | N65: =IFERROR(_xlfn.XLOOKUP(M65,EmployeeTable[Employee ID],EmployeeTable[Employee Name],"Not found"),IFERROR(INDEX(EmployeeTable[Employee Name],MATCH(M65,EmployeeTable[Employee ID],0)),"Not found")) -> Sana Khan | O65: Opening Checklist | P65: 46287 | Q65: 46288 | S65: Pending | T65: =IF(S65="Completed",IF(R65<=Q65,"On Time","Delayed"),IF(Q65<TODAY(),"Overdue","Pending")) -> Overdue | U65: =IF(S65="Completed",IF(R65<=Q65,1,0),0) -> 0
L66: TASK0062 | M66: E005 | N66: =IFERROR(_xlfn.XLOOKUP(M66,EmployeeTable[Employee ID],EmployeeTable[Employee Name],"Not found"),IFERROR(INDEX(EmployeeTable[Employee Name],MATCH(M66,EmployeeTable[Employee ID],0)),"Not found")) -> Ishaan Gupta | O66: Safety Inspection | P66: 46273 | Q66: 46275 | R66: 46276 | S66: Completed | T66: =IF(S66="Completed",IF(R66<=Q66,"On Time","Delayed"),IF(Q66<TODAY(),"Overdue","Pending")) -> Delayed | U66: =IF(S66="Completed",IF(R66<=Q66,1,0),0) -> 0
L67: TASK0063 | M67: E002 | N67: =IFERROR(_xlfn.XLOOKUP(M67,EmployeeTable[Employee ID],EmployeeTable[Employee Name],"Not found"),IFERROR(INDEX(EmployeeTable[Employee Name],MATCH(M67,EmployeeTable[Employee ID],0)),"Not found")) -> Diya Verma | O67: Stock Reconciliation | P67: 46284 | Q67: 46287 | R67: 46289 | S67: Completed | T67: =IF(S67="Completed",IF(R67<=Q67,"On Time","Delayed"),IF(Q67<TODAY(),"Overdue","Pending")) -> Delayed | U67: =IF(S67="Completed",IF(R67<=Q67,1,0),0) -> 0
L68: TASK0064 | M68: E009 | N68: =IFERROR(_xlfn.XLOOKUP(M68,EmployeeTable[Employee ID],EmployeeTable[Employee Name],"Not found"),IFERROR(INDEX(EmployeeTable[Employee Name],MATCH(M68,EmployeeTable[Employee ID],0)),"Not found")) -> Vivaan Joshi | O68: Customer Callback | P68: 46277 | Q68: 46279 | R68: 46278 | S68: Completed | T68: =IF(S68="Completed",IF(R68<=Q68,"On Time","Delayed"),IF(Q68<TODAY(),"Overdue","Pending")) -> On Time | U68: =IF(S68="Completed",IF(R68<=Q68,1,0),0) -> 1
L69: TASK0065 | M69: E006 | N69: =IFERROR(_xlfn.XLOOKUP(M69,EmployeeTable[Employee ID],EmployeeTable[Employee Name],"Not found"),IFERROR(INDEX(EmployeeTable[Employee Name],MATCH(M69,EmployeeTable[Employee ID],0)),"Not found")) -> Ananya Rao | O69: Document Review | P69: 46309 | Q69: 46311 | S69: In Progress | T69: =IF(S69="Completed",IF(R69<=Q69,"On Time","Delayed"),IF(Q69<TODAY(),"Overdue","Pending")) -> Overdue | U69: =IF(S69="Completed",IF(R69<=Q69,1,0),0) -> 0
L70: TASK0066 | M70: E003 | N70: =IFERROR(_xlfn.XLOOKUP(M70,EmployeeTable[Employee ID],EmployeeTable[Employee Name],"Not found"),IFERROR(INDEX(EmployeeTable[Employee Name],MATCH(M70,EmployeeTable[Employee ID],0)),"Not found")) -> Kabir Patel | O70: End-of-Day Closure | P70: 46299 | Q70: 46302 | R70: 46304 | S70: Completed | T70: =IF(S70="Completed",IF(R70<=Q70,"On Time","Delayed"),IF(Q70<TODAY(),"Overdue","Pending")) -> Delayed | U70: =IF(S70="Completed",IF(R70<=Q70,1,0),0) -> 0
L71: TASK0067 | M71: E010 | N71: =IFERROR(_xlfn.XLOOKUP(M71,EmployeeTable[Employee ID],EmployeeTable[Employee Name],"Not found"),IFERROR(INDEX(EmployeeTable[Employee Name],MATCH(M71,EmployeeTable[Employee ID],0)),"Not found")) -> Ira Nair | O71: Opening Checklist | P71: 46290 | Q71: 46292 | R71: 46292 | S71: Completed | T71: =IF(S71="Completed",IF(R71<=Q71,"On Time","Delayed"),IF(Q71<TODAY(),"Overdue","Pending")) -> On Time | U71: =IF(S71="Completed",IF(R71<=Q71,1,0),0) -> 1
L72: TASK0068 | M72: E007 | N72: =IFERROR(_xlfn.XLOOKUP(M72,EmployeeTable[Employee ID],EmployeeTable[Employee Name],"Not found"),IFERROR(INDEX(EmployeeTable[Employee Name],MATCH(M72,EmployeeTable[Employee ID],0)),"Not found")) -> Rohan Das | O72: Safety Inspection | P72: 46303 | Q72: 46306 | R72: 46306 | S72: Completed | T72: =IF(S72="Completed",IF(R72<=Q72,"On Time","Delayed"),IF(Q72<TODAY(),"Overdue","Pending")) -> On Time | U72: =IF(S72="Completed",IF(R72<=Q72,1,0),0) -> 1
L73: TASK0069 | M73: E004 | N73: =IFERROR(_xlfn.XLOOKUP(M73,EmployeeTable[Employee ID],EmployeeTable[Employee Name],"Not found"),IFERROR(INDEX(EmployeeTable[Employee Name],MATCH(M73,EmployeeTable[Employee ID],0)),"Not found")) -> Meera Singh | O73: Stock Reconciliation | P73: 46293 | Q73: 46295 | S73: In Progress | T73: =IF(S73="Completed",IF(R73<=Q73,"On Time","Delayed"),IF(Q73<TODAY(),"Overdue","Pending")) -> Overdue | U73: =IF(S73="Completed",IF(R73<=Q73,1,0),0) -> 0
L74: TASK0070 | M74: E001 | N74: =IFERROR(_xlfn.XLOOKUP(M74,EmployeeTable[Employee ID],EmployeeTable[Employee Name],"Not found"),IFERROR(INDEX(EmployeeTable[Employee Name],MATCH(M74,EmployeeTable[Employee ID],0)),"Not found")) -> Aarav Sharma | O74: Customer Callback | P74: 46270 | Q74: 46272 | R74: 46273 | S74: Completed | T74: =IF(S74="Completed",IF(R74<=Q74,"On Time","Delayed"),IF(Q74<TODAY(),"Overdue","Pending")) -> Delayed | U74: =IF(S74="Completed",IF(R74<=Q74,1,0),0) -> 0

Sheet Lists & Settings
A1: Lists & Settings
A2: Editable validation lists and workbook control parameters • All data is fictional
A4: Order Status | C4: Task Status | E4: Activity Status | G4: Activity Types | I4: Departments | K4: Stock Alert | M4: Employee Status
A5: Delivered | C5: Completed | E5: Completed | G5: Site Visit | I5: Operations | K5: OK | M5: Active
A6: Pending | C6: Pending | E6: Pending | G6: Stock Audit | I6: Field Operations | K6: REORDER | M6: On Leave
A7: Processing | C7: In Progress | E7: In Progress | G7: Customer Follow-up | I7: Warehouse | M7: Inactive
A8: Cancelled | E8: Cancelled | G8: Delivery Verification | I8: Customer Service
A9: Returned | G9: Document Collection
G10: Quality Check
A13: Control Parameter | B13: Active Setting
A14: As-of Date | B14: 46314
A15: Week Starts On | B15: Monday
A16: Currency | B16: INR (₹)
A18: Workbook Administration Notes
A19: Add new operational rows directly below each Excel Table (OrdersTable, InventoryTable, EmployeeTable, FMSTable, ChecklistTable); structured references and dashboards expand automatically.
